Workbook

Sheet Guide
A1: 명탐정 코난 TCG 카드 데이터 (cards.xlsx)
A3: 사용법 | B3: Cards 시트에서 카드 ID 를 검색(Ctrl+F)해 셀을 고치고 저장 → GitHub 에 올리면 자동 검증/변환/배포됩니다.
A4: 연결 키 | B4: 항상 카드 ID(id / card_id). 행 순서·정렬은 마음대로 바꿔도 됩니다.
A5: 시트 | B5: Cards=카드 기본 정보 / Abilities=능력(ab) 1개당 1행 / Ops=능력 안의 효과(primitive) 1개당 1행 / CardExtra=추가 필드 / Meta=최상위 항목
A6: 이미지 | B6: 이미지는 실제 파일로 관리합니다 (CardImage 폴더의 id_XXXX.jpg). Cards 시트의 image_file 열에 파일명을 적으면 게임에 반영됩니다 (cards.json 에는 경로만 저장, base64 없음). 새 이미지는 CardImage 폴더에 넣고 image_file 만 적으세요.
A7: own(소유자) | B7: 굵은 발동 조건/코스트(Abilities 의 cond/cost)에서 own 이 없으면 자기 쪽(self)입니다. 실제 효과 대상은 Ops 시트의 filter_own 열(self/opp/any 드롭다운)에서 관리합니다. 비워 두면 '미지정'으로 검증이 경고합니다.
A8: 메모 열 | B8: 열 이름 앞에 # 또는 _ 를 붙이면 변환 시 무시됩니다.
A10: 머리글 색 | B10: 의미
A11: 파랑 | B11: 연결 키(ID/번호) — 바꾸지 마세요 | C11: key
A12: 주황 | B12: 엔진 동작에 영향을 주는 값(색/AP/LP/효과 등) | C12: logic
A13: 초록 | B13: 표시용 텍스트 — 고쳐도 게임 로직은 바뀌지 않음 | C13: display
A14: 노랑 | B14: 참고용 메타데이터 | C14: meta
A15: 회색 | B15: 자동 계산 열 — 수정해도 무시됨 | C15: readonly
A17: 필드 | B17: 설명 / 구분
A18: id | B18: 카드 ID (연결 키, 바꾸지 마세요) | C18: 연결 키
A19: type | B19: 카드 종류 char/event/partner/case | C19: 엔진 동작
A20: color | B20: 색상 (여러 색은 / 로 연결) | C20: 엔진 동작
A21: lv | B21: 레벨 = FILE 코스트 | C21: 엔진 동작
A22: lv2 | B22: 사건 카드의 해결편 레벨 | C22: 엔진 동작
A23: ap | B23: AP (공격력) | C23: 엔진 동작
A24: lp | B24: LP (라이프) | C24: 엔진 동작
A25: kw | B25: 키워드 (assault, misread1, disguise, rapid, bullet …) | C25: 엔진 동작
A26: trait | B26: 특징 (쉼표로 구분) | C26: 엔진 동작
A27: n | B27: 카드명 | C27: 표시용
A28: fx | B28: 일본어 원문 효과 텍스트 (표시용, 엔진 동작에 영향 없음) | C28: 표시용
A29: extra | B29: 한국어 효과 설명 (표시용, 엔진 동작에 영향 없음) | C29: 표시용
... A48: params | B48: 효과 매개변수 (JSON 객체, 하위 ops 포함) | C48: 엔진 동작

Sheet Cards
A1: id | B1: type | C1: color | D1: lv | E1: lv2 | F1: ap | G1: lp | H1: kw | I1: trait | J1: n | K1: series | L1: fx | M1: extra | N1: image_file | O1: ab_count | P1: img_info
A2: id_0001 | B2: char | C2: blue | D2: 8 | F2: 7000 | G2: 2 | I2: 探偵,毛利探偵事務所,少年探偵団 | J2: 江戸川コナン | K2: P01 | L2: 【パートナー(青)】【ターン①】自分がネクストヒントで手札を使用したとき、そのカードのレベル以下のレベルのキャラを1枚まで選び、デッキの下に移す。 | M2: 【파트너(청)】【턴①】 자신이 넥스트 힌트로 손패를 사용했을 때, 그 카드의 레벨 이하의 레벨을 가진 캐릭터를 1장까지 골라 덱 아래로 옮긴다. | N2: id_0001.jpg | O2: =COUNTIF(Abilities!$A:$A,A2) -> 1 | P2: 716x1000 216KB
A3: id_0002 | B3: char | C3: blue | D3: 6 | F3: 4000 | G3: 1 | I3: 少年探偵団,科学者 | J3: 灰原哀 | K3: P01 | L3: 【絆】江戸川コナン 相手の能力や効果によって選ばれない。 【宣言】【スリープ】:手札からレベル5以下の特徴[少年探偵団]のキャラを1枚まで登場させる。カード名[江戸川コナン]を登場させた場合、カードを1枚引く。 | M3: 【인연】에도가와 코난: 상대의 능력이나 효과로 선택되지 않는다. 【선언】【슬립】: 손패에서 레벨 5 이하의 특징 [소년탐정단]인 캐릭터를 1장까지 등장시킨다. 카드명 [에도가와 코난]을 등장시킨 경우, 카드를 1장 뽑는다. | N3: id_0002.jpg | O3: =COUNTIF(Abilities!$A:$A,A3) -> 2 | P3: 716x1000 208KB
A4: id_0003 | B4: char | C4: blue | D4: 7 | F4: 6000 | G4: 0 | I4: 高校生,毛利探偵事務所,空手家 | J4: 毛利蘭 | K4: P01 | L4: 相手の現場にいるキャラがこのキャラとのコンタクトによってリムーブされたとき、 カードを1枚引く。 【パートナー(青)】【宣言】【ターン①】手札を1枚リムーブする：ターン終了時までこのキャラをAP＋1000し､突撃(登場したターンからすぐにアクションできる)を持つ。 | M4: 상대의 현장에 있는 캐릭터가 이 캐릭터와의 컨택트로 인해 리무브되었을 때, 카드를 1장 뽑는다. 【파트너(파랑)】【선언】【턴①】 손패를 1장 리무브한다: 턴 종료 시까지 이 캐릭터의 AP를 +1000 하고, 돌격(등장한 턴부터 바로 액션할 수 있다)을 얻는다. | N4: id_0003.jpg | O4: =COUNTIF(Abilities!$A:$A,A4) -> 2 | P4: 716x1000 210KB
A5: id_0004 | B5: char | C5: blue | D5: 5 | F5: 6000 | G5: 1 | I5: 探偵,毛利探偵事務所,少年探偵団 | J5: 江戸川コナン | K5: P01 | L5: 【ヒラメキ】(証拠からリムーブされるときに発動する) カードを1枚引く。 | M5: 【히라메키】(증거에서 리무브될 때 발동한다) 카드를 1장 뽑는다. | N5: id_0004.jpg | O5: =COUNTIF(Abilities!$A:$A,A5) -> 1 | P5: 716x1000 156KB
A6: id_0005 | B6: char | C6: blue | D6: 6 | F6: 5000 | G6: 1 | I6: 探偵,高校生 | J6: 工藤新一 | K6: P01 | L6: 【パートナー】【青】お互いの現場にキャラが合わせて6枚以上いる場合、手札にあるこのキャラはレベル4になる。 【宣言】デッキの下に移す:LP0以下の【青】のキャラを1枚まで選び、アクティブにする。 | M6: 【파트너】【청】 서로의 현장에 캐릭터가 합쳐서 6장 이상 있는 경우, 손패에 있는 이 캐릭터는 레벨 4가 된다. 【선언】덱 아래로 옮긴다: LP0 이하의 【청】 캐릭터를 1장까지 선택하고, 액티브로 한다. | N6: id_0005.jpg | O6: =COUNTIF(Abilities!$A:$A,A6) -> 2 | P6: 716x1000 179KB
A7: id_0006 | B7: char | C7: blue | D7: 6 | F7: 6000 | G7: 0 | I7: 探偵,毛利探偵事務所 | J7: 毛利小五郎 | K7: P01 | L7: 相手の現場にいるキャラがこのキャラとのコンタクトによってリムーブされたとき、 手札を1枚リムーブしてもよい。そうした場合、自分は証拠を1つ得る。 | M7: 상대의 현장에 있는 캐릭터가 이 캐릭터와의 컨택트로 인해 리무브되었을 때, 손패를 1장 리무브해도 된다. 그렇게 한 경우, 자신은 증거를 1개 얻는다. | N7: id_0006.jpg | O7: =COUNTIF(Abilities!$A:$A,A7) -> 1 | P7: 716x1000 164KB
A8: id_0007 | B8: char | C8: blue | D8: 4 | F8: 2000 | G8: 2 | I8: 探偵,毛利探偵事務所,少年探偵団 | J8: 江戸川コナン | K8: P01 | L8: このキャラはスリープ状態で登場する。 【ヒラメキ】(証拠からリムーブされるときに発動する)カードを1枚引く。 | M8: 이 캐릭터는 슬립 상태로 등장한다. 【히라메키】(증거에서 리무브될 때 발동한다) 카드를 1장 뽑는다. | N8: id_0007.jpg | O8: =COUNTIF(Abilities!$A:$A,A8) -> 2 | P8: 716x1000 191KB
A9: id_0008 | B9: char | C9: blue | D9: 7 | F9: 6000 | G9: 1 | I9: 発明家 | J9: 阿笠博士 | K9: P01 | L9: 【ターン①】能力や効果によってレベル6以下の特徴[少年探偵団]のキャラが自分の現場に登場したとき、その中から1枚をアクティブにし、ターン終了時までそのキャラに迅速(登場したターンからすぐに推理かアクションできる)を与える。 | M9: 【턴①】능력이나 효과에 의해 레벨 6 이하의 특징 [소년탐정단]의 캐릭터가 자신의 현장에 登場했을 때, 그중에서 1장을 액티브로 하고, 턴 종료 시까지 그 캐릭터에게 신속(登場한 턴부터 바로 추리나 액션을 할 수 있다)을 부여한다. | N9: id_0008.jpg | O9: =COUNTIF(Abilities!$A:$A,A9) -> 1 | P9: 716x1000 249KB
A10: id_0009 | B10: char | C10: blue | D10: 4 | F10: 3000 | G10: 1 | I10: 弁護士 | J10: 妃英理 | K10: P01 | L10: 【登場時】自分のデッキのカードを上から2枚見る。その中からLP0の【青】のキャラを1枚まで公開して手札に加え、残りを好きな順番でデッキの下に移す。 | M10: 【등장 시】자신의 덱 카드를 위에서 2장 본다. 그중에서 LP0의 【청】 캐릭터를 1장까지 공개하여 손패에 넣고, 나머지는 원하는 순서로 덱 아래로 옮긴다. | N10: id_0009.jpg | O10: =COUNTIF(Abilities!$A:$A,A10) -> 1 | P10: 716x1000 162KB
A11: id_0010 | B11: char | C11: blue | D11: 4 | F11: 5000 | G11: 0 | I11: 少年探偵団 | J11: 小嶋元太 | K11: P01 | L11: 【登場時】レベル3以上のキャラの能力やレベル3以上のイベントの効果によって登場した場合、レベル5以下のキャラを1枚まで選び、スリープさせる。 | M11: 【등장 시】레벨 3 이상의 캐릭터의 능력이나 레벨 3 이상의 이벤트의 효과로 등장한 경우, 레벨 5 이하의 캐릭터를 1장까지 선택하여 슬리프시킨다. | N11: id_0010.jpg | O11: =COUNTIF(Abilities!$A:$A,A11) -> 1 | P11: 716x1000 195KB
A12: id_0011 | B12: char | C12: blue | D12: 3 | F12: 3000 | G12: 1 | I12: 少年探偵団 | J12: 円谷光彦 | K12: P01 | L12: 【登場時】レベル3以上のキャラの能力やレベル3以上のイベントの効果によって登場した場合、キャラを1枚まで選び、ターン終了時までAP+2000する。 | M12: 【등장 시】레벨 3 이상의 캐릭터의 능력이나 레벨 3 이상의 이벤트의 효과로 등장한 경우, 캐릭터를 1장까지 선택하고, 턴 종료 시까지 AP+2000 한다. | N12: id_0011.jpg | O12: =COUNTIF(Abilities!$A:$A,A12) -> 1 | P12: 716x1000 214KB
A13: id_0012 | B13: char | C13: blue | D13: 4 | F13: 4000 | G13: 1 | I13: 少年探偵団,科学者 | J13: 灰原哀 | K13: D01 | L13: 【登場時】自分のデッキのカードを上から4枚見る。その中から【青】のカードを1枚まで公開して手札に加え、残りを好きな順番でデッキの下に移す。カードを手札に加えた場合、手札を1枚リムーブする。 【ヒラメキ】(証拠からリムーブされるときに発動する)カードを1枚引く。 | M13: 【등장 시】자신의 덱 위에서 카드를 4장 본다. 그중에서 【파랑】 카드를 1장까지 공개하여 손패에 넣고, 나머지는 원하는 순서로 덱 아래로 보낸다. 카드를 손패에 넣은 경우, 손패를 1장 리무브한다. 【번뜩임】(증거에서 리무브될 때 발동한다) 카드를 1장 뽑는다. | N13: id_0012.jpg | O13: =COUNTIF(Abilities!$A:$A,A13) -> 2 | P13: 716x1000 251KB
... A18: id_0017 | B18: char | C18: blue | D18: 3 | F18: 2000 | G18: 1 | I18: 少年探偵団 | J18: 吉田歩美 | K18: P01 | L18: 【登場時】レベル3以上のキャラの能力やレベル3以上のイベントの効果によって登場した場合、カードを1枚引く。 | M18: 【등장 시】 레벨 3 이상의 캐릭터의 능력이나 레벨 3 이상의 이벤트의 효과로 등장한 경우, 카드를 1장 뽑는다. | N18: id_0017.jpg | O18: =COUNTIF(Abilities!$A:$A,A18) -> 1 | P18: 716x1000 211KB
A19: id_0018 | B19: event | C19: blue | D19: 6 | J19: 少年探偵団 | K19: P01 | L19: 【パートナー】【青】手札を1枚リムーブする。自分のデッキのカードを上から6枚見る。その中からレベル4以下の特徴[少年探偵団]のキャラを2枚まで登場させ、残りをシャッフルしてデッキの下に移す。 | M19: 【파트너】【청】 손패를 1장 리무브한다. 자신의 덱 카드를 위에서 6장 본다. 그중에서 레벨 4 이하의 특징 [소년탐정단]을 가진 캐릭터를 2장까지 등장시키고, 나머지는 셔플해서 덱 아래로 옮긴다. | N19: id_0018.jpg | O19: =COUNTIF(Abilities!$A:$A,A19) -> 1 | P19: 716x1000 257KB
A20: id_0019 | B20: event | C20: blue | D20: 2 | J20: シャッフルロマンス | K20: P01 | L20: 自分のデッキのカードを上から5枚見る。その中からカードを1枚まで手札に加え、残りを好きな順番でデッキの下に移す。このイベントを自分の現場にいるキャラ1枚にセットする。 このイベントがセットされているキャラは「このキャラがコンタクトしたとき、そのコンタクト中、このキャラをAP+2000する。」を持つ。 【ヒラメキ】(証拠からリムーブされるときに発動する) カードを1枚引く。 | M20: 자신의 덱 카드를 위에서 5장 본다. 그 중에서 카드를 1장까지 손패에 추가하고, 나머지는 원하는 순서로 덱 아래로 옮긴다. 이 이벤트를 자신의 현장에 있는 캐릭터 1장에 세트한다. 이 이벤트가 세트되어 있는 캐릭터는 "이 캐릭터가 컨택트했을 때, 그 컨택트 중, 이 캐릭터를 AP+2000 한다."를 가진다. 【히라메키】(증거에서 리무브될 때 발동한다) 카드를 1장 뽑는다. | N20: id_0019.jpg | O20: =COUNTIF(Abilities!$A:$A,A20) -> 3 | P20: 716x1000 202KB
A21: id_0020 | B21: case | C21: blue | D21: 7 | E21: 6 | J21: 大阪“3つのK”事件 | K21: P01 | N21: id_0020.jpg | O21: =COUNTIF(Abilities!$A:$A,A21) -> 0 | P21: 1000x716 150KB
A22: id_0021 | B22: char | C22: green | D22: 7 | F22: 5000 | G22: 0 | I22: 高校生 | J22: 遠山和葉 | K22: P01 | L22: 【パートナー(緑)】LP+1 【宣言】【スリープ】：カード名［服部平次］のキャラを1枚まで選び、ターン終了時まで突撃（登場したターンからすぐにアクションできる）を与える。 | M22: 【파트너(녹)】 LP+1 【선언】【슬립】: 카드명 [핫토리 헤이지]인 캐릭터를 1장까지 선택하고, 턴 종료 시까지 돌격(등장한 턴부터 바로 액션할 수 있다)을 부여한다. | N22: id_0021.jpg | O22: =COUNTIF(Abilities!$A:$A,A22) -> 2 | P22: 716x1000 223KB
A23: id_0022 | B23: char | C23: green | D23: 8 | F23: 7000 | G23: 2 | I23: 探偵,高校生 | J23: 服部平次 | K23: P01 | L23: このキャラは相手の現場にいるアクティブ状態のキャラを指定してアクションできる。 このキャラがコンタクトしたとき、そのコンタクト中、このキャラをAP＋1000する。 【パートナー(緑)】【自分ターン中】【ターン①】このキャラがコンタクトしたとき、このキャラをアクティブにする。 | M23: 이 캐릭터는 상대의 현장에 있는 액티브 상태의 캐릭터를 지정하여 액션할 수 있다. 이 캐릭터가 컨택트했을 때, 그 컨택트 중 이 캐릭터의 AP를 +1000 한다. 【파트너(녹)】【자신 턴 중】【턴①】 이 캐릭터가 컨택트했을 때, 이 캐릭터를 액티브로 한다. | N23: id_0022.jpg | O23: =COUNTIF(Abilities!$A:$A,A23) -> 3 | P23: 716x1000 211KB
A24: id_0023 | B24: char | C24: green | D24: 5 | F24: 6000 | G24: 1 | I24: 探偵,高校生 | J24: 服部平次 | K24: P01 | L24: 【ヒラメキ】(証拠からリムーブされるときに発動する)カードを1枚引く。 | M24: 【히라메키】(증거에서 리무브될 때 발동한다) 카드를 1장 뽑는다. | N24: id_0023.jpg | O24: =COUNTIF(Abilities!$A:$A,A24) -> 1 | P24: 716x1000 176KB
A25: id_0024 | B25: char | C25: green | D25: 5 | F25: 4000 | G25: 1 | I25: 高校生 | J25: 大岡紅葉 | K25: P01 | L25: 【ターン①】相手の現場にいるキャラがコンタクトによってリムーブされたとき、自分のリムーブエリアにある【カットイン】を持つ【緑】のカードを1枚まで選び、手札に加える。 | M25: 【턴①】 상대의 현장에 있는 캐릭터가 컨택트로 인해 리무브되었을 때, 자신의 리무브 에리어에 있는 【컷인】을 가진 【녹색】 카드를 1장까지 선택하여 손패에 넣는다. | N25: id_0024.jpg | O25: =COUNTIF(Abilities!$A:$A,A25) -> 1 | P25: 716x1000 236KB
A26: id_0025 | B26: char | C26: green | D26: 6 | F26: 5000 | G26: 1 | I26: 執事 | J26: 伊織無我 | K26: P01 | L26: 相手の現場にいるキャラがコンタクトによってリムーブされたとき、ターン終了時までこのキャラは突撃（登場したターンからすぐにアクションできる）を持つ。 | M26: 상대의 현장에 있는 캐릭터가 콘택트에 의해 리무브되었을 때, 턴 종료 시까지 이 캐릭터는 돌격(등장한 턴부터 바로 액션할 수 있다)을 가진다. | N26: id_0025.jpg | O26: =COUNTIF(Abilities!$A:$A,A26) -> 1 | P26: 716x1000 202KB
A27: id_0026 | B27: char | C27: green | D27: 3 | F27: 3000 | G27: 1 | I27: 探偵,高校生 | J27: 服部平次 | K27: D06 | L27: 【ターン①】このキャラがアクション［キャラ］したとき、ターン終了時までこのキャラをAP+1000する。 | M27: 【턴①】이 캐릭터가 액션[캐릭터]을 했을 때, 턴 종료 시까지 이 캐릭터를 AP+1000 한다. | N27: id_0026.jpg | O27: =COUNTIF(Abilities!$A:$A,A27) -> 1 | P27: 716x1000 203KB
A28: id_0027 | B28: char | C28: green | D28: 2 | F28: 1000 | G28: 1 | I28: 高校生 | J28: 遠山和葉 | L28: 【カットイン】AP＋2000（コンタクト中に手札からリムーブして使う） | M28: 【컷인】AP+2000 (컨택트 중에 손패에서 리무브하여 사용한다) | N28: id_0027.jpg | O28: =COUNTIF(Abilities!$A:$A,A28) -> 1 | P28: 716x1000 191KB
A29: id_0028 | B29: char | C29: green | D29: 4 | F29: 4000 | G29: 1 | I29: 高校生 | J29: 大岡紅葉 | K29: P01 | L29: 【登場時】自分のデッキのカードを上から4枚見る。その中から【緑】のカードを1枚まで公開して手札に加え、残りを好きな順番でデッキの下に移す。カードを手札に加えた場合、手札を1枚リムーブする。 【ヒラメキ】(証拠からリムーブされるときに発動する)カードを1枚引く。 | M29: 【등장 시】자신의 덱 카드를 위에서 4장 본다. 그중에서 【녹색】 카드를 1장까지 공개하여 손패에 더하고, 나머지는 원하는 순서로 덱 아래로 옮긴다. 카드를 손패에 더한 경우, 손패를 1장 리무브한다. 【힌트(번뜩임)】(증거에서 리무브될 때 발동한다) 카드를 1장 뽑는다. | N29: id_0028.jpg | O29: =COUNTIF(Abilities!$A:$A,A29) -> 2 | P29: 716x1000 221KB
A30: id_0029 | B30: char | C30: green | D30: 4 | F30: 4000 | G30: 1 | I30: 警察,大阪府警 | J30: 大滝悟郎 | K30: D06 | L30: 【現場リムーブ時】コンタクトによってリムーブされた場合、キャラを1枚まで選び、スリープさせる。 【ヒラメキ】(証拠からリムーブされるときに発動する)カードを1枚引く。 | M30: 【현장 리무브 시】 컨택트에 의해 리무브된 경우, 캐릭터를 1장까지 선택해 슬리프시킨다. 【히라메키】(증거에서 리무브될 때 발동한다) 카드를 1장 뽑는다. | N30: id_0029.jpg | O30: =COUNTIF(Abilities!$A:$A,A30) -> 2 | P30: 716x1000 184KB
A31: id_0030 | B31: char | C31: green | D31: 6 | F31: 6000 | G31: 1 | I31: 警察,大阪府警 | J31: 遠山銀司郎 | K31: P01 | L31: 【ターン①】自分の現場にいる【緑】のキャラがアクション[キャラ]したとき、キャラを1枚まで選び、スリープさせる。 | M31: 【턴①】자신의 현장에 있는 【녹】 캐릭터가 액션[캐릭터]했을 때, 캐릭터를 1장까지 선택하여 슬리프시킨다. | N31: id_0030.jpg | O31: =COUNTIF(Abilities!$A:$A,A31) -> 1 | P31: 716x1000 168KB
A32: id_0031 | B32: char | C32: green | D32: 3 | F32: 3000 | G32: 1 | J32: 服部静華 | K32: P01 | L32: 【ターン①】自分の現場にいる【緑】のキャラがアクション[キャラ]したとき、カードを1枚引き、手札を1枚リムーブする。 【ヒラメキ】(証拠からリムーブされるときに発動する)カードを1枚引く。 | M32: 【턴①】자신의 현장에 있는 【녹】 캐릭터가 액션[캐릭터]했을 때, 카드를 1장 뽑고 손패를 1장 리무브한다. 【힌트(ヒラメキ)】(증거에서 리무브될 때 발동한다) 카드를 1장 뽑는다. | N32: id_0031.jpg | O32: =COUNTIF(Abilities!$A:$A,A32) -> 2 | P32: 716x1000 232KB
A33: id_0032 | B33: char | C33: green | D33: 6 | F33: 6000 | G33: 1 | I33: 警察,大阪府警 | J33: 服部平蔵 | K33: P01 | L33: 【自分ターン中】自分の現場にいるこのキャラ以外の【緑】のキャラをAP＋1000する。 【ヒラメキ】(証拠からリムーブされるときに発動する)カードを1枚引く。 | M33: 【자신 턴 중】 자신의 현장에 있는 이 캐릭터 이외의 【녹】 캐릭터를 AP+1000 한다. 【히라메키】(증거에서 리무브될 때 발동한다) 카드를 1장 뽑는다. | N33: id_0032.jpg | O33: =COUNTIF(Abilities!$A:$A,A33) -> 2 | P33: 716x1000 225KB
A34: id_0033 | B34: event | C34: green | D34: 5 | J34: 「かっ…和葉ァ!!!」 | K34: P01 | L34: このイベントを自分の現場にいる【緑】のキャラ1枚にセットする。 このイベントがセットされているキャラが相手の能力や効果、コンタクトによって現場から離れるとき、このイベントをリムーブし、そのキャラは現場から離れる代わりに現場に残る。 | M34: 이 이벤트를 자신의 현장에 있는 【녹색】 캐릭터 1장에게 세트한다. 이 이벤트가 세트되어 있는 캐릭터가 상대의 능력이나 효과, 컨택트에 의해 현장에서 떠날 때, 이 이벤트를 리무브하고, 그 캐릭터는 현장에서 떠나는 대신 현장에 남는다. | N34: id_0033.jpg | O34: =COUNTIF(Abilities!$A:$A,A34) -> 2 | P34: 716x1000 266KB
A35: id_0034 | B35: event | C35: green | D35: 3 | J35: 「オレの和葉に何さらしとんじゃ!!!」 | K35: D06 | L35: キャラを1枚まで選び、スリープさせる。カードを1枚引く。 【ヒラメキ】(証拠からリムーブされるときに発動する)キャラを1枚まで選び、スリープさせる。 | M35: 캐릭터를 1장까지 선택하여 슬립시킨다. 카드를 1장 뽑는다. 【히라메키】(증거에서 리무브될 때 발동한다) 캐릭터를 1장까지 선택하여 슬립시킨다. | N35: id_0034.jpg | O35: =COUNTIF(Abilities!$A:$A,A35) -> 2 | P35: 716x1000 231KB
A36: id_0035 | B36: case | C36: green | D36: 7 | E36: 6 | J36: コナンと平次 恋の暗号 | K36: P01 | N36: id_0035.jpg | O36: =COUNTIF(Abilities!$A:$A,A36) -> 0 | P36: 1000x716 185KB
A37: id_0036 | B37: char | C37: white | D37: 8 | F37: 7000 | G37: 2 | I37: 怪盗 | J37: 怪盗キッド | K37: P01 | L37: 【パートナー(白)】【登場時】自分のデッキのカードを上から7枚リムーブしてもよい。 そうした場合、キャラを1枚まで選び、デッキの下に移す。 | M37: 【파트너(백)】【등장 시】 자신의 덱의 카드를 위에서 7장 리무브해도 좋다. 그렇게 한 경우, 캐릭터를 1장까지 골라 덱의 아래로 옮긴다. | N37: id_0036.jpg | O37: =COUNTIF(Abilities!$A:$A,A37) -> 1 | P37: 716x1000 177KB
A38: id_0037 | B38: char | C38: blue | D38: 6 | F38: 5000 | G38: 1 | H38: misread1 | I38: 高校生 | J38: 中森青子 | K38: P01 | L38: ミスリード1（相手の推理に対し、スリープさせることでLP－1する） 【ターン①】相手の現場にいるキャラが推理かアクションしたとき、自分のデッキのカードを上から5枚リムーブしてもよい。そうした場合、ターン終了時までそのキャラを元のLPを0にし、元のAPを0にする。 | M38: 미스리드 1 (상대의 추리에 대해, 슬리프시킴으로써 LP-1 한다) 【턴①】상대의 현장에 있는 캐릭터가 추리나 액션을 했을 때, 자신의 덱 카드를 위에서 5장 리무브해도 된다. 그렇게 한 경우, 턴 종료 시까지 그 캐릭터의 원래 LP를 0으로 하고, 원래 AP를 0으로 한다. | N38: id_0037.jpg | O38: =COUNTIF(Abilities!$A:$A,A38) -> 2 | P38: 716x1000 195KB
A39: id_0038 | B39: char | C39: white | D39: 5 | F39: 6000 | G39: 1 | I39: 怪盗 | J39: 怪盗キッド | K39: P01 | L39: 【ヒラメキ】(証拠からリムーブされるときに発動する) カードを1枚引く。 | M39: 【히라메키】(증거에서 리무브될 때 발동한다) 카드를 1장 뽑는다. | N39: id_0038.jpg | O39: =COUNTIF(Abilities!$A:$A,A39) -> 1 | P39: 716x1000 227KB
A40: id_0039 | B40: char | C40: white | D40: 5 | F40: 4000 | G40: 1 | I40: 高校生 | J40: 黒羽快斗 | K40: P01 | L40: このキャラのアクション終了時、このキャラを現場からデッキの下に移してもよい。そうした場合、手札からレベル6以下の【白】のカード名[黒羽快斗]以外のキャラを1枚まで登場させる。ターン終了時までそのキャラに【突撃】(登場したターンからすぐにアクションできる)と「ターン終了時、このキャラを現場から手札に移す。」を与える。 | M40: 이 캐릭터의 액션 종료 시, 이 캐릭터를 현장에서 덱 아래로 옮겨도 된다. 그렇게 한 경우, 손패에서 레벨 6 이하의 【백】 카드명 [쿠로바 카이토] 이외의 캐릭터를 1장까지 등장시킨다. 턴 종료 시까지 그 캐릭터에게 【돌격】(등장한 턴부터 바로 액션할 수 있다)과 「턴 종료 시, 이 캐릭터를 현장에서 손패로 옮긴다.」를 부여한다. | N40: id_0039.jpg | O40: =COUNTIF(Abilities!$A:$A,A40) -> 1 | P40: 716x1000 179KB
A41: id_0040 | B41: char | C41: white | D41: 5 | F41: 5000 | G41: 1 | I41: 高校生,鈴木財閥 | J41: 鈴木園子 | K41: P01 | L41: 【宣言】【スリープ】：自分のデッキのカードを上から3枚見る。その中からカードを1枚手札に加え、残りを好きな順番でデッキの下に移す。 【ヒラメキ】(証拠からリムーブされるときに発動する)キャラを1枚まで選び、スリープさせる。 | M41: 【선언】【슬립】: 자신의 덱 카드를 위에서 3장 본다. 그 중에서 카드를 1장 손패에 넣고, 나머지는 원하는 순서로 덱 아래에 둔다. 【번뜩임】(증거에서 리무브될 때 발동한다) 캐릭터를 1장까지 선택하고, 슬립시킨다. | N41: id_0040.jpg | O41: =COUNTIF(Abilities!$A:$A,A41) -> 2 | P41: 716x1000 222KB
A42: id_0041 | B42: char | C42: white | D42: 3 | F42: 3000 | G42: 1 | I42: 怪盗 | J42: 怪盗キッド | K42: P01 | L42: 【自分ターン中】相手の現場にキャラが3枚以上いる場合、このキャラをAP+2000する。 | M42: 【자신 턴 중】 상대의 현장에 캐릭터가 3장 이상 있는 경우, 이 캐릭터는 AP+2000 된다. | N42: id_0041.jpg | O42: =COUNTIF(Abilities!$A:$A,A42) -> 1 | P42: 716x1000 192KB
A43: id_0042 | B43: char | C43: white | D43: 6 | F43: 4000 | G43: 2 | I43: 怪盗 | J43: 怪盗1412号 | K43: P01 | L43: このキャラはスリープ状態で登場する。 【登場時】自分のデッキのカードを上から1枚公開する。公開したカードが【白】のカードの場合、手札に加える。公開したカードがそれ以外の場合、デッキの下に移す。 【ヒラメキ】(証拠からリムーブされるときに発動する)カードを1枚引く。 | M43: 이 캐릭터는 슬리프 상태로 등장한다. 【등장 시】 자신의 덱 카드를 위에서 1장 공개한다. 공개한 카드가 【백】 카드인 경우 손패에 추가한다. 공개한 카드가 그 이외인 경우 덱 아래로 옮긴다. 【히라메키】(증거에서 리무브될 때 발동한다) 카드를 1장 뽑는다. | N43: id_0042.jpg | O43: =COUNTIF(Abilities!$A:$A,A43) -> 3 | P43: 716x1000 213KB
A44: id_0043 | B44: char | C44: white | D44: 7 | F44: 6000 | G44: 0 | H44: assault-char | I44: 高校生,空手家 | J44: 京極真 | K44: P01 | L44: 突撃【キャラ】(登場したターンからすぐにキャラを指定してアクションできる) このキャラは事件を指定してアクションできない。 【自分ターン中】AP+1000 | M44: 돌격【캐릭터】(등장한 턴부터 바로 캐릭터를 지정해서 액션할 수 있다) 이 캐릭터는 사건을 지정해서 액션할 수 없다. 【자신 턴 중】AP+1000 | N44: id_0043.jpg | O44: =COUNTIF(Abilities!$A:$A,A44) -> 3 | P44: 716x1000 216KB
A45: id_0044 | B45: char | C45: white | D45: 7 | F45: 5000 | G45: 2 | I45: 小説家 | J45: 工藤優作 | K45: P01 | L45: このキャラはスリープ状態で登場する。 【登場時】自分のデッキのカードを上から1枚公開する。公開したカードがレベル6以下のキャラの場合、登場させる。公開したカードがそれ以外の場合、手札に加える。 | M45: 이 캐릭터는 슬리프 상태로 등장한다. 【등장 시】자신의 덱 카드를 위에서 1장 공개한다. 공개한 카드가 레벨 6 이하의 캐릭터인 경우, 등장시킨다. 공개한 카드가 그 이외의 경우, 손패에 추가한다. | N45: id_0044.jpg | O45: =COUNTIF(Abilities!$A:$A,A45) -> 2 | P45: 716x1000 218KB
A46: id_0045 | B46: char | C46: white | D46: 4 | F46: 3000 | G46: 1 | J46: 工藤有希子 | K46: P01 | L46: 【登場時】自分のデッキのカードを上から2枚見る。その中からLP2以上の【白】のキャラを1枚まで公開して手札に加え、残りを好きな順番でデッキの下に移す。 | M46: 【등장 시】 자신의 덱 카드를 위에서 2장 본다. 그 중에서 LP2 이상의 【백】 캐릭터를 1장까지 공개하여 손패에 추가하고, 나머지는 원하는 순서로 덱 아래로 옮긴다. | N46: id_0045.jpg | O46: =COUNTIF(Abilities!$A:$A,A46) -> 1 | P46: 716x1000 227KB
A47: id_0046 | B47: char | C47: white | D47: 3 | F47: 3000 | G47: 1 | J47: 寺井黄之助 | K47: P01 | L47: 【相手ターン中】【現場リムーブ時】キャラを1枚まで選び、ターン終了時まで元のLPを0にする。 【ヒラメキ】(証拠からリムーブされるときに発動する)カードを1枚引く。 | M47: 【상대 턴 중】【현장 리무브 시】 캐릭터를 1장까지 선택하고, 턴 종료 시까지 원래 LP를 0으로 한다. 【히라메키】(증거에서 리무브될 때 발동한다) 카드를 1장 뽑는다. | N47: id_0046.jpg | O47: =COUNTIF(Abilities!$A:$A,A47) -> 2 | P47: 716x1000 187KB
A48: id_0047 | B48: char | C48: white | D48: 4 | F48: 4000 | G48: 1 | I48: 高校生,鈴木財閥 | J48: 鈴木園子 | K48: P01 | L48: 【登場時】自分のデッキのカードを上から4枚見る。その中から【白】のカードを1枚まで公開して手札に加え、残りを好きな順番でデッキの下に移す。カードを手札に加えた場合、手札を1枚リムーブする。 【ヒラメキ】(証拠からリムーブされるときに発動する)カードを1枚引く。 | M48: 【등장 시】자신의 덱 카드를 위에서 4장 본다. 그 중에서 【백】 카드를 1장까지 공개하여 손패에 더하고, 나머지는 원하는 순서로 덱 아래로 보낸다. 카드를 손패에 더한 경우, 손패를 1장 리무브한다. 【히라메키】(증거에서 리무브될 때 발동한다) 카드를 1장 뽑는다. | N48: id_0047.jpg | O48: =COUNTIF(Abilities!$A:$A,A48) -> 2 | P48: 716x1000 212KB
A49: id_0048 | B49: char | C49: white | D49: 2 | F49: 1000 | G49: 1 | I49: 探偵,高校生 | J49: 白馬探 | K49: P01 | L49: 【カットイン】AP＋2000(コンタクト中に手札からリムーブして使う) | M49: 【컷인】AP+2000 (컨택트 중에 손패에서 리무브하여 사용한다) | N49: id_0048.jpg | O49: =COUNTIF(Abilities!$A:$A,A49) -> 1 | P49: 716x1000 241KB
A50: id_0049 | B50: event | C50: white | D50: 5 | J50: 「最も出会いたくない…恋人ってトコロかな?」 | K50: P01 | L50: このイベントを自分の現場にいる【白】のキャラ1枚にセットする。 このイベントがセットされているキャラは「【相手ターン中】【現場リムーブ時】手札からレベル7以下の【白】のキャラを1枚まで登場させる。」を持つ。 【ヒラメキ】(証拠からリムーブされるときに発動する)カードを1枚引く。 | M50: 이 이벤트를 자신의 현장에 있는 【백】 캐릭터 1장에게 세트한다. 이 이벤트가 세트된 캐릭터는 "【상대 턴 중】【현장 리무브 시】 손패에서 레벨 7 이하의 【백】 캐릭터를 1장까지 등장시킨다."를 가진다. 【ヒラメキ】(증거에서 리무브될 때 발동한다) 카드를 1장 뽑는다. | N50: id_0049.jpg | O50: =COUNTIF(Abilities!$A:$A,A50) -> 3 | P50: 716x1000 202KB
A51: id_0050 | B51: event | C51: white | D51: 4 | J51: トッ | K51: P01 | L51: 【白】のキャラを1枚まで選び、ターン終了時まで【突撃[事件]】を与える。このターン中、次に相手の証拠がリムーブされたとき、スリープ状態のキャラを1枚まで選び、スタンさせる。(スタン状態のキャラをアクティブにする場合、代わりにスリープさせる) | M51: 【백】 캐릭터를 1장까지 선택하고, 턴 종료 시까지 【돌격[사건]】을 부여한다. 이 턴 중, 다음에 상대의 증거가 리무브되었을 때, 슬립 상태의 캐릭터를 1장까지 선택하고 스턴시킨다. (스턴 상태의 캐릭터를 액티브로 하는 경우, 대신 슬립시킨다) | N51: id_0050.jpg | O51: =COUNTIF(Abilities!$A:$A,A51) -> 1 | P51: 716x1000 229KB
A52: id_0051 | B52: case | C52: white | D52: 7 | E52: 6 | J52: 怪盗キッドの瞬間移動魔術 | K52: P01 | N52: id_0051.jpg | O52: =COUNTIF(Abilities!$A:$A,A52) -> 0 | P52: 1000x716 296KB
A53: id_0052 | B53: char | C53: red | D53: 8 | F53: 7000 | G53: 2 | I53: FBI,赤井家 | J53: 赤井秀一 | K53: P01 | L53: 【パートナー】【赤】【ターン①】自分の現場にいるキャラがアクション[事件]したとき、レベル7以下のキャラを1枚まで選び、リムーブする。 【宣言】【ターン①】【赤】のキャラを1枚まで選び、ターン終了時までAP+1000する。 | M53: 【파트너】【적】【턴①】자신의 현장에 있는 캐릭터가 액션[사건]했을 때, 레벨 7 이하의 캐릭터를 1장까지 선택하여 리무브한다. 【선언】【턴①】【적】 캐릭터를 1장까지 선택하고, 턴 종료 시까지 AP+1000 한다. | N53: id_0052.jpg | O53: =COUNTIF(Abilities!$A:$A,A53) -> 2 | P53: 716x1000 193KB
A54: id_0053 | B54: char | C54: red | D54: 7 | F54: 5000 | G54: 1 | I54: FBI | J54: ジョディ・スターリング | K54: P01 | L54: 【宣言】【スリープ】このキャラ以外のキャラを1枚スリープさせる:レベル7以下のキャラを1枚まで選び、リムーブする。 | M54: 【선언】【슬립】이 캐릭터 이외의 캐릭터를 1장 슬립시킨다: 레벨 7 이하의 캐릭터를 1장까지 선택하여 리무브한다. | N54: id_0053.jpg | O54: =COUNTIF(Abilities!$A:$A,A54) -> 1 | P54: 716x1000 188KB
A55: id_0054 | B55: char | C55: red | D55: 5 | F55: 6000 | G55: 1 | I55: FBI,赤井家 | J55: 赤井秀一 | K55: P01 | L55: 【ヒラメキ】(証拠からリムーブされるときに発動する)カードを1枚引く。 | M55: 【히라메키】(증거에서 리무브될 때 발동한다) 카드를 1장 뽑는다. | N55: id_0054.jpg | O55: =COUNTIF(Abilities!$A:$A,A55) -> 1 | P55: 716x1000 193KB
A56: id_0055 | B56: char | C56: red | D56: 5 | F56: 5000 | G56: 1 | I56: 大学院生 | J56: 沖矢昴 | K56: P01 | L56: 【相手ターン中】【現場リムーブ時】相手に証拠を1つ与えてもよい。そうした場合、レベル5以下のキャラを1枚まで選び、リムーブする。 【ヒラメキ】(証拠からリムーブされるときに発動する)キャラを1枚まで選び、スリープさせる。 | M56: 【상대 턴 중】【현장 리무브 시】 상대에게 증거를 1개 줘도 된다. 그렇게 한 경우, 레벨 5 이하의 캐릭터를 1장까지 선택하여 리무브한다. 【히라메키】(증거에서 리무브될 때 발동한다) 캐릭터를 1장까지 선택하여 슬립시킨다. | N56: id_0055.jpg | O56: =COUNTIF(Abilities!$A:$A,A56) -> 2 | P56: 716x1000 204KB
A57: id_0056 | B57: char | C57: red | D57: 6 | F57: 6000 | G57: 1 | I57: 探偵,高校生,赤井家 | J57: 世良真純 | K57: P01 | L57: 【ターン①】このキャラがアクション[事件]したとき、このキャラをアクティブにする。 | M57: 【턴①】이 캐릭터가 액션[사건]했을 때, 이 캐릭터를 액티브로 한다. | N57: id_0056.jpg | O57: =COUNTIF(Abilities!$A:$A,A57) -> 1 | P57: 716x1000 158KB
A58: id_0057 | B58: char | C58: red | D58: 5 | F58: 4000 | G58: 1 | I58: 赤井家 | J58: メアリー | K58: P01 | L58: このキャラのアクション[事件]によって証拠を得たとき、相手の現場にいるレベル5以下のキャラを1枚まで選び、手札に移す。 | M58: 이 캐릭터의 액션 [사건]으로 증거를 얻었을 때, 상대의 현장에 있는 레벨 5 이하의 캐릭터를 1장까지 선택하여 손패로 옮긴다. | N58: id_0057.jpg | O58: =COUNTIF(Abilities!$A:$A,A58) -> 1 | P58: 716x1000 175KB
A59: id_0058 | B59: char | C59: red | D59: 3 | F59: 3000 | G59: 1 | I59: FBI,赤井家 | J59: 赤井秀一 | K59: P01 | L59: このキャラがアクション[事件]したとき、ターン終了時までこのキャラはブレット (このキャラのアクションはガードできない)を持つ。 | M59: 이 캐릭터가 액션[사건]했을 때, 턴 종료 시까지 이 캐릭터는 블렛(이 캐릭터의 액션은 가드할 수 없다)을 가진다. | N59: id_0058.jpg | O59: =COUNTIF(Abilities!$A:$A,A59) -> 1 | P59: 716x1000 231KB
A60: id_0059 | B60: char | C60: red | D60: 4 | F60: 4000 | G60: 1 | I60: 赤井家 | J60: 赤井務武 | K60: P01 | L60: 【登場時】相手に証拠を1つ与えてもよい。そうした場合、カードを1枚引く。 | M60: 【등장 시】 상대에게 증거를 1개 줘도 된다. 그렇게 한 경우, 카드를 1장 뽑는다. | N60: id_0059.jpg | O60: =COUNTIF(Abilities!$A:$A,A60) -> 1 | P60: 716x1000 157KB
A61: id_0060 | B61: char | C61: red | D61: 6 | F61: 6000 | G61: 0 | I61: FBI | J61: アンドレ・キャメル | K61: P01 | L61: 相手の現場にいるキャラがこのキャラを指定してアクションしたとき、そのコンタクト中、このキャラをAP＋1000する。 【宣言】【スリープ】：キャラを1枚まで選び、ターン終了時までブレット（このキャラのアクションはガードできない）を与える。 【ヒラメキ】(証拠からリムーブされるときに発動する）カードを1枚引く。 | M61: 상대의 현장에 있는 캐릭터가 이 캐릭터를 지정해서 액션했을 때, 그 컨택트 중 이 캐릭터는 AP+1000 된다. 【선언】【슬립】: 캐릭터를 1장까지 선택하고, 턴 종료 시까지 블렛(이 캐릭터의 액션은 가드할 수 없다)을 부여한다. 【히라메키】(증거에서 리무브될 때 발동한다) 카드를 1장 뽑는다. | N61: id_0060.jpg | O61: =COUNTIF(Abilities!$A:$A,A61) -> 3 | P61: 716x1000 186KB
A62: id_0061 | B62: char | C62: red | D62: 7 | F62: 6000 | G62: 1 | I62: FBI | J62: ジェイムズ・ブラック | K62: P01 | L62: 【ターン①】自分の現場にいる特徴［FBI］のキャラがアクションしたとき、カードを1枚引く。 【ターン①】相手の現場にいるキャラが自分の現場にいる特徴［FBI］のキャラを指定してアクションしたとき、カードを1枚引く。 | M62: 【턴①】자신의 현장에 있는 특징 [FBI] 캐릭터가 액션했을 때, 카드를 1장 뽑는다. 【턴①】상대의 현장에 있는 캐릭터가 자신의 현장에 있는 특징 [FBI] 캐릭터를 지정하여 액션했을 때, 카드를 1장 뽑는다. | N62: id_0061.jpg | O62: =COUNTIF(Abilities!$A:$A,A62) -> 2 | P62: 716x1000 197KB
A63: id_0062 | B63: char | C63: red | D63: 4 | F63: 4000 | G63: 1 | I63: FBI | J63: ジョディ・スターリング | K63: D04 | L63: 【登場時】自分のデッキのカードを上から4枚見る。その中から【赤】のカードを1枚まで公開して手札に加え、残りを好きな順番でデッキの下に移す。カードを手札に加えた場合、手札を1枚リムーブする。 【ヒラメキ】(証拠からリムーブされるときに発動する)カードを1枚引く。 | M63: 【등장 시】자신의 덱 카드를 위에서 4장 본다. 그중에서 【빨강】 카드를 1장까지 공개하여 손패에 더하고, 나머지는 원하는 순서로 덱 아래로 옮긴다. 카드를 손패에 더한 경우, 손패를 1장 리무브한다. 【번뜩임】(증거에서 리무브될 때 발동한다) 카드를 1장 뽑는다. | N63: id_0062.jpg | O63: =COUNTIF(Abilities!$A:$A,A63) -> 2 | P63: 716x1000 233KB
A64: id_0063 | B64: char | C64: red | D64: 2 | F64: 1000 | G64: 1 | I64: 探偵,高校生,赤井家 | J64: 世良真純 | L64: 【カットイン】AP＋2000（コンタクト中に手札からリムーブして使う） | M64: 【컷인】AP+2000 (컨택트 중에 손패에서 리무브하여 사용한다) | N64: id_0063.jpg | O64: =COUNTIF(Abilities!$A:$A,A64) -> 1 | P64: 716x1000 218KB
A65: id_0064 | B65: char | C65: red | D65: 4 | F65: 4000 | G65: 1 | I65: 棋士,赤井家 | J65: 羽田秀吉 | K65: P01 | L65: このキャラが推理したとき、相手は手札を公開する。(その後、元に戻す) 【ヒラメキ】(証拠からリムーブされるときに発動する) カードを 1 枚引く。 | M65: 이 캐릭터가 추리했을 때, 상대는 손패를 공개한다. (그 후 원래대로 되돌린다) 【ヒラメキ】(증거에서 리무브될 때 발동한다) 카드를 1장 뽑는다. | N65: id_0064.jpg | O65: =COUNTIF(Abilities!$A:$A,A65) -> 2 | P65: 716x1000 203KB
A66: id_0065 | B66: char | C66: red | D66: 3 | F66: 3000 | G66: 1 | J66: 宮野明美 | K66: P01 | L66: 【相手ターン中】【ターン①】このキャラか自分の現場にいる【赤】のキャラがリムーブされたとき、カードを1枚引き、手札を1枚リムーブする。 【ヒラメキ】(証拠からリムーブされるときに発動する) カードを1枚引く。 | M66: 【상대 턴 중】【턴①】이 캐릭터나 자신의 현장에 있는 【적】 캐릭터가 리무브되었을 때, 카드를 1장 뽑고 손패를 1장 리무브한다. 【히라메키】(증거에서 리무브될 때 발동한다) 카드를 1장 뽑는다. | N66: id_0065.jpg | O66: =COUNTIF(Abilities!$A:$A,A66) -> 2 | P66: 716x1000 172KB
A67: id_0066 | B67: event | C67: red | D67: 6 | J67: 「開けるんだキャメル…」 | K67: P01 | L67: 自分のリムーブエリアにあるレベル6以下の【赤】のキャラを1枚まで選び、登場させる。 | M67: 자신의 리무브 에리어에 있는 레벨 6 이하의 【적】 캐릭터를 1장까지 선택하여 登場(등장)시킨다. | N67: id_0066.jpg | O67: =COUNTIF(Abilities!$A:$A,A67) -> 1 | P67: 716x1000 186KB
A68: id_0067 | B68: event | C68: red | D68: 4 | J68: 「赤井…秀一!?」 | K68: P01 | L68: 【パートナー(赤)】相手は手札を1枚ランダムにリムーブする。キャラを1枚まで選び、ターン終了時までブレット(このキャラのアクションはガードできない)を与える。 【ヒラメキ】(証拠からリムーブされるときに発動する)相手は手札を1枚リムーブする。 | M68: 【파트너(적)】 상대는 손패를 1장 랜덤으로 리무브한다. 캐릭터를 1장까지 선택하고, 턴 종료 시까지 블렛(이 캐릭터의 액션은 가드할 수 없다)을 부여한다. 【히라메키】(증거에서 리무브될 때 발동한다) 상대는 손패를 1장 리무브한다. | N68: id_0067.jpg | O68: =COUNTIF(Abilities!$A:$A,A68) -> 2 | P68: 716x1000 170KB
A69: id_0068 | B69: case | C69: red | D69: 7 | E69: 6 | J69: 17年前と同じ現場 | K69: P01 | N69: id_0068.jpg | O69: =COUNTIF(Abilities!$A:$A,A69) -> 0 | P69: 1000x716 206KB
A70: id_0069 | B70: char | C70: yellow | D70: 8 | F70: 7000 | G70: 2 | I70: 探偵,喫茶ポアロ | J70: 安室透 | K70: P01 | L70: 【パートナー(黄)】【ターン①】自分の現場にいるキャラがアクションしたとき、レベル7以下のキャラを1枚まで選び、デッキの上か下に移す。(自分が上か下かを選ぶ) | M70: 【파트너(노랑)】【턴①】자신의 현장에 있는 캐릭터가 액션했을 때, 레벨 7 이하의 캐릭터를 1장까지 선택하여 덱의 위나 아래로 옮긴다. (자신이 위인지 아래인지 선택한다) | N70: id_0069.jpg | O70: =COUNTIF(Abilities!$A:$A,A70) -> 1 | P70: 716x1000 180KB
A71: id_0070 | B71: char | C71: yellow | D71: 7 | F71: 4000 | G71: 1 | I71: 喫茶ポアロ | J71: 榎本梓 | K71: P01 | L71: 【パートナー】【黄】このキャラはアクションできず、ガードできない。相手の現場にいるキャラはこのキャラを指定してアクションできない。 【登場時】レベル7以下のキャラを1枚まで選び、スリープさせる。このキャラが現場にいるかぎり、選んだキャラはオートフェイズにアクティブにならない。 | M71: 【파트너】【노랑】이 캐릭터는 액션할 수 없고, 가드할 수 없다. 상대의 현장에 있는 캐릭터는 이 캐릭터를 지정해서 액션할 수 없다. 【등장 시】레벨 7 이하의 캐릭터를 1장까지 선택하고, 슬립시킨다. 이 캐릭터가 현장에 있는 한, 선택한 캐릭터는 오토 페이즈에 액티브가 되지 않는다. | N71: id_0070.jpg | O71: =COUNTIF(Abilities!$A:$A,A71) -> 2 | P71: 716x1000 193KB
A72: id_0071 | B72: char | C72: yellow | D72: 5 | F72: 6000 | G72: 1 | I72: 探偵,喫茶ポアロ | J72: 安室透 | K72: P01 | L72: 【ヒラメキ】(証拠からリムーブされるときに発動する)カードを1枚引く。 | M72: 【히라메키】(증거에서 리무브될 때 발동한다) 카드를 1장 뽑는다. | N72: id_0071.jpg | O72: =COUNTIF(Abilities!$A:$A,A72) -> 1 | P72: 716x1000 227KB
A73: id_0072 | B73: char | C73: yellow | D73: 6 | F73: 6000 | G73: 1 | I73: 警察,公安 | J73: 降谷零 | K73: P01 | L73: 自分のターン終了時、捜査1（相手はデッキのカードを上から指定の数だけ公開し、好きな順番でデッキの下に移す）する。レベル5以上のカードが発見された場合、このキャラ以外のレベル6以下のキャラを1枚まで選び、アクティブにする。 | M73: 자신의 턴 종료 시, 수사 1을 한다(상대는 덱의 카드를 위에서 지정된 수만큼 공개하고, 원하는 순서로 덱 아래로 옮긴다). 레벨 5 이상의 카드가 발견된 경우, 이 캐릭터 이외의 레벨 6 이하 캐릭터를 1장까지 골라 액티브로 한다. | N73: id_0072.jpg | O73: =COUNTIF(Abilities!$A:$A,A73) -> 1 | P73: 716x1000 167KB
A74: id_0073 | B74: char | C74: yellow | D74: 3 | F74: 3000 | G74: 1 | I74: 探偵,喫茶ポアロ | J74: 安室透 | K74: P01 | L74: このキャラがアクションしたとき、捜査1（相手はデッキのカードを上から指定の数だけ公開し、好きな順番でデッキの下に移す）する。レベル5以上のカードが発見された場合、ターン終了時までこのキャラをAP+2000する。 | M74: 이 캐릭터가 액션했을 때, 수사 1을 한다(상대는 덱의 카드를 위에서 지정한 수만큼 공개하고, 원하는 순서로 덱의 아래로 옮긴다). 레벨 5 이상의 카드가 발견된 경우, 턴 종료 시까지 이 캐릭터의 AP를 +2000 한다. | N74: id_0073.jpg | O74: =COUNTIF(Abilities!$A:$A,A74) -> 1 | P74: 716x1000 231KB
A75: id_0074 | B75: char | C75: yellow | D75: 2 | F75: 1000 | G75: 1 | I75: 喫茶ポアロ | J75: 榎本梓 | K75: P01 | L75: 【カットイン】AP＋2000（コンタクト中に手札からリムーブして使う） | M75: 【컷인】AP+2000 (컨택트 중에 손패에서 리무브하여 사용한다) | N75: id_0074.jpg | O75: =COUNTIF(Abilities!$A:$A,A75) -> 1 | P75: 716x1000 209KB
A76: id_0075 | B76: char | C76: yellow | D76: 6 | F76: 5000 | G76: 1 | I76: 警察,警視庁,公安 | J76: 風見裕也 | K76: P01 | L76: 【絆】降谷零【宣言】【ターン①】ターン終了時までこのキャラをLP+1するか、AP+2000する。 【ヒラメキ】(証拠からリムーブされるときに発動する)カードを1枚引く。 | M76: 【인연】후루야 레이【선언】【턴①】턴 종료 시까지 이 캐릭터를 LP+1 하거나 AP+2000 한다. 【히라메키】(증거에서 리무브될 때 발동한다) 카드를 1장 뽑는다. | N76: id_0075.jpg | O76: =COUNTIF(Abilities!$A:$A,A76) -> 2 | P76: 716x1000 180KB
A77: id_0076 | B77: char | C77: yellow | D77: 6 | F77: 5000 | G77: 1 | I77: 警察,警視庁 | J77: 黒田兵衛 | K77: P01 | L77: 【宣言】【ターン①】【スリープ】手札を1枚リムーブする:このキャラ以外のレベル8以下の【黄】のキャラを1枚まで選び、ターン終了時まで突撃[キャラ](登場したターンからすぐにキャラを指定してアクションできる)を与える。 | M77: 【선언】【턴①】【슬리프】손패를 1장 리무브한다: 이 캐릭터 이외의 레벨 8 이하의 【노랑】 캐릭터를 1장까지 선택하고, 턴 종료 시까지 돌격[캐릭터](등장한 턴부터 바로 캐릭터를 지정하여 액션할 수 있다)를 부여한다. | N77: id_0076.jpg | O77: =COUNTIF(Abilities!$A:$A,A77) -> 1 | P77: 716x1000 187KB
A78: id_0077 | B78: char | C78: yellow | D78: 5 | F78: 5000 | G78: 1 | I78: 警察,警視庁 | J78: 佐藤美和子 | K78: P01 | L78: 【相手ターン中】【ターン①】このキャラか自分の現場にいる【黄】のキャラがリムーブされたとき、カードを1枚引く。 【ヒラメキ】(証拠からリムーブされるときに発動する)キャラを1枚まで選び、スリープさせる。 | M78: 【상대 턴 중】【턴①】이 캐릭터나 자신의 현장에 있는 【노랑】 캐릭터가 리무브되었을 때, 카드를 1장 뽑는다. 【히라메키】(증거에서 리무브될 때 발동한다) 캐릭터를 1장까지 골라 슬리프시킨다. | N78: id_0077.jpg | O78: =COUNTIF(Abilities!$A:$A,A78) -> 2 | P78: 716x1000 202KB
A79: id_0078 | B79: char | C79: yellow | D79: 4 | F79: 4000 | G79: 1 | I79: 警察,警視庁 | J79: 佐藤美和子 | K79: P01 | L79: 【登場時】自分のデッキのカードを上から4枚見る。その中から【黄】のカードを1枚まで公開して手札に加え、残りを好きな順番でデッキの下に移す。カードを手札に加えた場合、手札を1枚リムーブする。 【ヒラメキ】(証拠からリムーブされるときに発動する)カードを1枚引く。 | M79: 【등장 시】자신의 덱 카드를 위에서 4장 본다. 그중에서 【노랑】 카드를 1장까지 공개하여 손패에 더하고, 나머지는 원하는 순서로 덱 아래로 옮긴다. 카드를 손패에 더한 경우, 손패를 1장 리무브한다. 【번뜩임】(증거에서 리무브될 때 발동한다) 카드를 1장 뽑는다. | N79: id_0078.jpg | O79: =COUNTIF(Abilities!$A:$A,A79) -> 2 | P79: 716x1000 229KB
A80: id_0079 | B80: char | C80: yellow | D80: 6 | F80: 5000 | G80: 1 | I80: 警察,警視庁 | J80: 高木渉 | K80: P01 | L80: 【絆】佐藤美和子【自分ターン中】AP+3000 【ヒラメキ】(証拠からリムーブされるときに発動する）キャラを1枚まで選び、スリープさせる。 | M80: 【인연】사토 미와코 【자신 턴 중】AP+3000 【히라메키】(증거에서 리무브될 때 발동한다) 캐릭터를 1장까지 선택하고, 슬립시킨다. | N80: id_0079.jpg | O80: =COUNTIF(Abilities!$A:$A,A80) -> 2 | P80: 716x1000 190KB
A81: id_0080 | B81: char | C81: yellow | D81: 6 | F81: 6000 | G81: 1 | I81: 警察,警視庁 | J81: 松田陣平 | K81: P01 | L81: 【相手ターン中】自分の現場にいるこのキャラ以外のキャラ1枚が相手の能力や効果、コンタクトによって現場から離れるとき、このキャラをリムーブしてもよい。そうした場合、そのキャラは現場から離れる代わりに手札に移す。 【ヒラメキ】(証拠からリムーブされるときに発動する)カードを1枚引く。 | M81: 【상대 턴 중】자신의 현장에 있는 이 캐릭터 이외의 캐릭터 1장이 상대의 능력이나 효과, 콘택트에 의해 현장에서 떠날 때, 이 캐릭터를 리무브해도 된다. 그렇게 한 경우, 그 캐릭터는 현장에서 떠나는 대신 손패로 이동한다. 【히라메키】(증거에서 리무브될 때 발동한다) 카드를 1장 뽑는다. | N81: id_0080.jpg | O81: =COUNTIF(Abilities!$A:$A,A81) -> 2 | P81: 716x1000 191KB
A82: id_0081 | B82: char | C82: yellow | D82: 4 | F82: 3000 | G82: 1 | H82: misread1 | I82: 警察,警視庁 | J82: 目暮十三 | K82: P01 | L82: ミスリード1(相手の推理に対し、スリープさせることでLP-1する) 【登場時】相手はデッキのカードを上から1枚公開する。そのカードをデッキの上か下に移す。(自分が上か下かを選ぶ) 【ヒラメキ】(証拠からリムーブされるときに発動する)カードを1枚引く。 | M82: 미스리드 1 (상대의 추리에 대해, 슬립시킴으로써 LP-1 한다) 【등장 시】 상대는 덱의 카드를 위에서 1장 공개한다. 그 카드를 덱의 위나 아래로 옮긴다. (자신이 위인지 아래인지 고른다) 【히라메키】 (증거에서 리무브될 때 발동한다) 카드를 1장 뽑는다. | N82: id_0081.jpg | O82: =COUNTIF(Abilities!$A:$A,A82) -> 3 | P82: 716x1000 188KB
A83: id_0082 | B83: event | C83: yellow | D83: 3 | J83: 「刑事なら刑事らしく…」 | K83: P01 | L83: 自分のリムーブエリアにある【黄】のキャラを1枚まで選び、手札に加える。レベル7以下のキャラを1枚まで選び、ターン終了時まで突撃［キャラ］(登場したターンからすぐにキャラを指定してアクションできる)を与える。 【ヒラメキ】(証拠からリムーブされるときに発動する)自分のリムーブエリアにある【黄】のキャラを1枚まで選び、手札に加える。 | M83: 자신의 리무브 에리어에 있는 【노랑】 캐릭터를 1장까지 골라 손패에 추가한다. 레벨 7 이하의 캐릭터를 1장까지 골라 턴 종료 시까지 돌격[캐릭터](등장한 턴부터 바로 캐릭터를 지정하여 액션할 수 있다)을 부여한다. 【히라메키】(증거에서 리무브될 때 발동한다) 자신의 리무브 에리어에 있는 【노랑】 캐릭터를 1장까지 골라 손패에 추가한다. | N83: id_0082.jpg | O83: =COUNTIF(Abilities!$A:$A,A83) -> 2 | P83: 716x1000 224KB
A84: id_0083 | B84: event | C84: yellow | D84: 7 | J84: 「僕の日本から…」 | K84: P01 | L84: 【パートナー(黄)】カード名を1つ指定し、捜査1（相手はデッキのカードを上から指定の数だけ公開し、好きな順番でデッキの下に移す）する。指定したカード名のカードが発見された場合、キャラを2枚まで選び、スタンさせる。（スタン状態のキャラをアクティブにする場合、代わりにスリープさせる） | M84: 【파트너(노랑)】카드명을 1개 지정하고 수사 1을 한다(상대는 덱의 카드를 위에서부터 지정한 수만큼 공개하고, 원하는 순서로 덱 아래로 옮긴다). 지정한 카드명의 카드가 발견된 경우, 캐릭터를 2장까지 선택하여 스탠시킨다. (스탠 상태의 캐릭터를 액티브로 하는 경우, 대신 슬립시킨다) | N84: id_0083.jpg | O84: =COUNTIF(Abilities!$A:$A,A84) -> 1 | P84: 716x1000 229KB
A85: id_0084 | B85: case | C85: yellow | D85: 7 | E85: 6 | J85: ギスギスしたお茶会 | K85: P01 | N85: id_0084.jpg | O85: =COUNTIF(Abilities!$A:$A,A85) -> 0 | P85: 1000x716 169KB
A86: id_0085 | B86: char | C86: black | D86: 4 | F86: 5000 | G86: 0 | I86: 黒ずくめの組織 | J86: ウォッカ | K86: P01 | L86: 【カットイン】カードを2枚引き、手札を1枚リムーブする。(コンタクト中に手札からリムーブして使う) | M86: 【컷인】카드를 2장 뽑고, 손패를 1장 리무브한다. (컨택트 중에 손패에서 리무브하여 사용한다) | N86: id_0085.jpg | O86: =COUNTIF(Abilities!$A:$A,A86) -> 1 | P86: 716x1000 142KB
A87: id_0086 | B87: char | C87: black | D87: 6 | F87: 6000 | G87: 1 | I87: 黒ずくめの組織 | J87: ジン | L87: 【カットイン】【自分ターン中】(自分のターンのコンタクト中に手札からリムーブすることで発動する)コンタクト中のすべてのキャラをリムーブする。 | M87: 【컷인】【자신 턴 중】(자신의 턴 컨택트 중에 손패에서 리무브함으로써 발동한다) 컨택트 중인 모든 캐릭터를 리무브한다. | N87: id_0086.jpg | O87: =COUNTIF(Abilities!$A:$A,A87) -> 1 | P87: 716x1000 327KB
A88: id_0087 | B88: case | C88: green/blue | D88: 7 | E88: 6 | J88: どっちの推理ショー | K88: P01 | L88: この事件が解決編になったとき、相手はカードを1枚引く。 | M88: 이 사건이 해결편이 되었을 때, 상대는 카드를 1장 뽑는다. | N88: id_0087.jpg | O88: =COUNTIF(Abilities!$A:$A,A88) -> 1 | P88: 1000x716 173KB
A89: id_0088 | B89: case | C89: blue/white | D89: 7 | E89: 6 | J89: 怪盗キッドの絡繰箱 | K89: P01 | L89: この事件が解決編になったとき、相手はカードを1枚引く。 | M89: 이 사건이 해결편이 되었을 때, 상대는 카드를 1장 뽑는다. | N89: id_0088.jpg | O89: =COUNTIF(Abilities!$A:$A,A89) -> 1 | P89: 1000x716 195KB
A90: id_0089 | B90: case | C90: red/blue | D90: 7 | E90: 6 | J90: 赤と黒のクラッシュ | K90: P01 | L90: この事件が解決編になったとき、相手はカードを1枚引く。 | M90: 이 사건이 해결편이 되었을 때, 상대는 카드를 1장 뽑는다. | N90: id_0089.jpg | O90: =COUNTIF(Abilities!$A:$A,A90) -> 1 | P90: 1000x716 191KB
A91: id_0090 | B91: case | C91: blue/yellow | D91: 7 | E91: 6 | J91: 牧場に墜ちた火種 | K91: P01 | L91: この事件が解決編になったとき、相手はカードを1枚引く。 | M91: 이 사건이 해결편이 되었을 때, 상대는 카드를 1장 뽑는다. | N91: id_0090.jpg | O91: =COUNTIF(Abilities!$A:$A,A91) -> 1 | P91: 1000x716 228KB
A92: id_0091 | B92: char | C92: blue | D92: 7 | F92: 6000 | G92: 1 | I92: 探偵,毛利探偵事務所,少年探偵団 | J92: 江戸川コナン | K92: D01 | L92: 【パートナー】【青】迅速（登場したターンからすぐに推理かアクションできる） | M92: 【파트너】【청】신속 (등장한 턴부터 바로 추리나 액션을 할 수 있다) | N92: id_0091.jpg | O92: =COUNTIF(Abilities!$A:$A,A92) -> 1 | P92: 716x1000 172KB
A93: id_0092 | B93: char | C93: blue | D93: 4 | F93: 4000 | G93: 1 | I93: 探偵,毛利探偵事務所,少年探偵団 | J93: 江戸川コナン | K93: D01 | L93: 【宣言】【ターン①】このキャラ以外のキャラを1枚スリープさせる:カードを1枚引き、 手札を1枚リムーブする。ターン終了時までこのキャラをLP+1する。 【ヒラメキ】(証拠からリムーブされるときに発動する)カードを1枚引く。 | M93: 【선언】【턴①】이 캐릭터 이외의 캐릭터를 1장 슬립시킨다: 카드를 1장 뽑고, 손패를 1장 리무브한다. 턴 종료 시까지 이 캐릭터를 LP+1 한다. 【번뜩임】(증거에서 리무브될 때 발동한다) 카드를 1장 뽑는다. | N93: id_0092.jpg | O93: =COUNTIF(Abilities!$A:$A,A93) -> 2 | P93: 716x1000 211KB
A94: id_0093 | B94: char | C94: blue | D94: 8 | F94: 7000 | G94: 2 | I94: 探偵,高校生 | J94: 工藤新一 | L94: 【パートナー(青)】【登場時】手札を1枚リムーブしてもよい。そうした場合、AP8000以下のキャラを1枚まで選び、リムーブする。 | M94: 【파트너(청)】【등장 시】 손패를 1장 리무브해도 된다. 그렇게 한 경우, AP8000 이하의 캐릭터를 1장까지 선택하여 리무브한다. | N94: id_0093.jpg | O94: =COUNTIF(Abilities!$A:$A,A94) -> 1 | P94: 716x1000 188KB
A95: id_0094 | B95: char | C95: blue | D95: 5 | F95: 5000 | G95: 0 | I95: 探偵,毛利探偵事務所 | J95: 毛利小五郎 | K95: D10 | L95: 【パートナー(青)】突撃 (登場したターンからすぐにアクションできる) | M95: 【파트너(청)】돌격 (등장한 턴부터 바로 액션할 수 있다) | N95: id_0094.jpg | O95: =COUNTIF(Abilities!$A:$A,A95) -> 1 | P95: 716x1000 197KB
A96: id_0095 | B96: char | C96: blue | D96: 6 | F96: 6000 | G96: 0 | I96: 高校生,毛利探偵事務所,空手家 | J96: 毛利蘭 | K96: D01 | L96: 【宣言】【ターン①】キャラを1枚まで選び、ターン終了時までAP+1000する。 【登場時】キャラを1枚まで選び、ターン終了時までAP+1000する。 【ヒラメキ】(証拠からリムーブされるときに発動する)カードを1枚引く。 | M96: 【선언】【턴①】캐릭터를 1장까지 선택하고, 턴 종료 시까지 AP+1000 한다. 【등장 시】캐릭터를 1장까지 선택하고, 턴 종료 시까지 AP+1000 한다. 【히라메키】(증거에서 리무브될 때 발동한다) 카드를 1장 뽑는다. | N96: id_0095.jpg | O96: =COUNTIF(Abilities!$A:$A,A96) -> 3 | P96: 716x1000 187KB
A97: id_0096 | B97: char | C97: blue | D97: 3 | F97: 2000 | G97: 1 | I97: 高校生,毛利探偵事務所,空手家 | J97: 毛利蘭 | K97: D08 | L97: 【カットイン】AP＋2000（コンタクト中に手札からリムーブして使う） | M97: 【컷인】AP+2000 (컨택트 중에 손패에서 리무브하여 사용한다) | N97: id_0096.jpg | O97: =COUNTIF(Abilities!$A:$A,A97) -> 1 | P97: 716x1000 172KB
A98: id_0097 | B98: char | C98: blue | D98: 6 | F98: 5000 | G98: 1 | I98: 発明家 | J98: 阿笠博士 | K98: D01 | L98: 【登場時】手札からレベル4以下の特徴［少年探偵団］のキャラを1枚までスリープ状態で登場させてもよい。登場させなかった場合、キャラを1枚まで選び、ターン終了時までAP＋1000する。 | M98: 【등장 시】 손패에서 레벨 4 이하의 특징 [소년탐정단]을 가진 캐릭터를 1장까지 슬리프 상태로 등장시켜도 된다. 등장시키지 않은 경우, 캐릭터를 1장까지 선택하고 턴 종료 시까지 AP+1000 한다. | N98: id_0097.jpg | O98: =COUNTIF(Abilities!$A:$A,A98) -> 1 | P98: 716x1000 242KB
A99: id_0098 | B99: char | C99: blue | D99: 4 | F99: 4000 | G99: 1 | I99: 少年探偵団 | J99: 吉田歩美 | K99: D01 | L99: 【カットイン】AP＋1000（コンタクト中に手札からリムーブして使う） | M99: 【컷인】AP+1000 (컨택트 중에 손패에서 리무브하여 사용한다) | N99: id_0098.jpg | O99: =COUNTIF(Abilities!$A:$A,A99) -> 1 | P99: 716x1000 212KB
A100: id_0099 | B100: char | C100: blue | D100: 3 | F100: 2000 | G100: 1 | H100: misread1 | I100: 少年探偵団 | J100: 円谷光彦 | K100: D01 | L100: ミスリード１（相手の推理に対し、スリープさせることでLP－1する） 【カットイン】AP＋1000（コンタクト中に手札からリムーブして使う） | M100: 미스리드 1 (상대의 추리에 대해, 슬리프시키는 것으로 LP -1 한다) 【컷인】AP +1000 (컨택트 중에 손패에서 리무브하여 사용한다) | N100: id_0099.jpg | O100: =COUNTIF(Abilities!$A:$A,A100) -> 2 | P100: 716x1000 221KB
A101: id_0100 | B101: char | C101: blue | D101: 2 | F101: 1000 | G101: 1 | I101: 少年探偵団 | J101: 小嶋元太 | K101: D01 | L101: 【カットイン】AP＋2000（コンタクト中に手札からリムーブして使う） | M101: 【컷인】AP+2000 (컨택트 중에 손패에서 리무브하여 사용한다) | N101: id_0100.jpg | O101: =COUNTIF(Abilities!$A:$A,A101) -> 1 | P101: 716x1000 185KB
A102: id_0101 | B102: char | C102: blue | D102: 5 | F102: 5000 | G102: 1 | I102: 少年探偵団,科学者 | J102: 灰原哀 | K102: D01 | L102: 【相手ターン中】【現場リムーブ時】自分のデッキのカードを上から3枚見る。その中からレベル4以下の【青】のキャラを1枚までスリープ状態で登場させ、残りを好きな順番でデッキの下に移す。 【ヒラメキ】(証拠からリムーブされるときに発動する)キャラを1枚まで選び、スリープさせる。 | M102: 【상대 턴 중】【현장 리무브 시】 자신의 덱 카드를 위에서 3장 본다. 그 중에서 레벨 4 이하의 【청】 캐릭터를 1장까지 슬리프 상태로 登場시키고, 나머지는 원하는 순서로 덱 아래로 옮긴다. 【히라메키】(증거에서 리무브될 때 발동한다) 캐릭터를 1장까지 골라 슬리프시킨다. | N102: id_0101.jpg | O102: =COUNTIF(Abilities!$A:$A,A102) -> 2 | P102: 716x1000 185KB
A103: id_0102 | B103: event | C103: blue | D103: 1 | J103: 小さくなった名探偵 | K103: D01 | L103: 自分のデッキのカードを上から3枚見る。その中から【青】のキャラを1枚まで公開して手札に加え、残りを好きな順番でデッキの下に移す。手札から自分のFILEエリアの枚数以下のレベルの【青】のキャラを1枚まで登場させる。 | M103: 자신의 덱 카드를 위에서 3장 본다. 그중에서 【파랑】 캐릭터를 1장까지 공개하여 손패에 추가하고, 나머지를 원하는 순서로 덱 아래로 옮긴다. 손패에서 자신의 FILE 에리어의 장수 이하의 레벨인 【파랑】 캐릭터를 1장까지 등장시킨다. | N103: id_0102.jpg | O103: =COUNTIF(Abilities!$A:$A,A103) -> 1 | P103: 716x1000 212KB
A104: id_0103 | B104: event | C104: blue | D104: 5 | J104: 蘭の一撃 | K104: D08 | L104: 【パートナー(青)】(パートナーが条件を満たしている場合、この能力か効果を使える)AP8000以下のキャラを1枚まで選び、リムーブする。 | M104: 【파트너(청)】(파트너가 조건을 충족하고 있는 경우, 이 능력이나 효과를 사용할 수 있다) AP8000 이하의 캐릭터를 1장까지 선택하고, 리무브한다. | N104: id_0103.jpg | O104: =COUNTIF(Abilities!$A:$A,A104) -> 1 | P104: 716x1000 247KB
...

Sheet Abilities
A1: card_id | B1: ab_index | C1: ic | D1: txt | E1: lim | F1: cond | G1: tgt | H1: cost | I1: ops | J1: v | K1: kw | L1: evs | M1: who | N1: sf | O1: ap | P1: sub | Q1: pa | R1: ef | S1: by | T1: g | U1: hay | V1: k | W1: pk | X1: lp | Y1: per | Z1: lv | AA1: cz | AB1: tr | AC1: tself | AD1: nm | AE1: st | AF1: tApLow | AG1: tf | AH1: alt | AI1: lvd | AJ1: az | AK1: hself | AL1: hw | AM1: sw | AN1: fromHand | AO1: on | AP1: bang | AQ1: dself | AR1: first | AS1: fromRem | AT1: fromUp | AU1: gab | AV1: incl | AW1: rep | AX1: ops_count
A2: id_0001 | B2: 0 | C2: onhint | D2: 【パートナー(青)】【ターン1】自分がネクストヒントで手札を使用したとき、そのカードのレベル以下のレベルのキャラを1枚まで選び、デッキの下に移す。 | E2: 1 | F2: {"pcolor":"blue"} | I2: →Ops | AX2: 1
A3: id_0002 | B3: 0 | C3: static | D3: 【絆】江戸川コナン 相手の能力や効果によって選ばれない。 | F3: {"bond":"江戸川コナン"} | G3: {"sel":"self"} | K3: untarget | AX3: 0
A4: id_0002 | B4: 1 | C4: declare | D4: 【宣言】【スリープ】:手札からレベル5以下の特徴[少年探偵団]のキャラを1枚まで登場させる。カード名[江戸川コナン]を登場させた場合、カードを1枚引く。 | H4: [{"c":"sleepSelf","n":1}] | I4: →Ops | AX4: 2
A5: id_0003 | B5: 0 | C5: onkill | D5: 相手の現場にいるキャラがこのキャラとのコンタクトによってリムーブされたとき、カードを1枚引く。 | I5: →Ops | AX5: 1
A6: id_0003 | B6: 1 | C6: declare | D6: 【パートナー(青)】【宣言】【ターン1】手札を1枚リムーブする:ターン終了時までこのキャラをAP+1000し、突撃(登場したターンからすぐにアクションできる)を持つ。 | E6: 1 | F6: {"pcolor":"blue"} | H6: [{"c":"discard","n":1}] | I6: →Ops | AX6: 2
A7: id_0004 | B7: 0 | C7: flash | D7: 【ヒラメキ】(証拠からリムーブされるときに発動する) カードを1枚引く。 | I7: →Ops | AX7: 1
A8: id_0005 | B8: 0 | C8: hand | D8: 【パートナー】【青】お互いの現場にキャラが合わせて6枚以上いる場合、手札にあるこのキャラはレベル4になる。 | F8: {"pcolor":"blue","fieldMin":6} | Z8: 4 | AX8: 0
A9: id_0005 | B9: 1 | C9: declare | D9: 【宣言】デッキの下に移す:LP0以下の【青】のキャラを1枚まで選び、アクティブにする。 | H9: [{"c":"selfBottom","n":1}] | I9: →Ops | AX9: 1
A10: id_0006 | B10: 0 | C10: onkill | D10: 相手の現場にいるキャラがこのキャラとのコンタクトによってリムーブされたとき、手札を1枚リムーブしてもよい。そうした場合、自分は証拠を1つ得る。 | I10: →Ops | AX10: 2
A11: id_0007 | B11: 0 | C11: enter | D11: このキャラはスリープ状態で登場する。 | AE11: s | AX11: 0
A12: id_0007 | B12: 1 | C12: flash | D12: 【ヒラメキ】(証拠からリムーブされるときに発動する)カードを1枚引く。 | I12: →Ops | AX12: 1
A13: id_0008 | B13: 0 | C13: onally | D13: 【ターン1】能力や効果によってレベル6以下の特徴[少年探偵団]のキャラが自分の現場に登場したとき、その中から1枚をアクティブにし、ターン終了時までそのキャラに迅速(登場したターンからすぐに推理かアクションできる)を与える。 | E13: 1 | I13: →Ops | R13: {"trait":"少年探偵団","lvMax":6,"own":"self"} | AO13: {"by":"effect"} | AX13: 2
A14: id_0009 | B14: 0 | C14: onplay | D14: 【登場時】自分のデッキのカードを上から2枚見る。その中からLP0の【青】のキャラを1枚まで公開して手札に加え、残りを好きな順番でデッキの下に移す。 | I14: →Ops | AX14: 1
A15: id_0010 | B15: 0 | C15: onplay | D15: 【登場時】レベル3以上のキャラの能力やレベル3以上のイベントの効果によって登場した場合、レベル5以下のキャラを1枚まで選び、スリープさせる。 | F15: {"via":[{"type":"char","lvMin":3},{"type":"event","lvMin":3}]} | I15: →Ops | AX15: 1
A16: id_0011 | B16: 0 | C16: onplay | D16: 【登場時】レベル3以上のキャラの能力やレベル3以上のイベントの効果によって登場した場合、キャラを1枚まで選び、ターン終了時までAP+2000する。 | F16: {"via":[{"type":"char","lvMin":3},{"type":"event","lvMin":3}]} | I16: →Ops | AX16: 1
A17: id_0012 | B17: 0 | C17: onplay | D17: 【登場時】自分のデッキのカードを上から4枚見る。その中から【青】のカードを1枚まで公開して手札に加え、残りを好きな順番でデッキの下に移す。カードを手札に加えた場合、手札を1枚リムーブする。 | I17: →Ops | AX17: 2
A18: id_0012 | B18: 1 | C18: flash | D18: 【ヒラメキ】(証拠からリムーブされるときに発動する)カードを1枚引く。 | I18: →Ops | AX18: 1
A19: id_0013 | B19: 0 | C19: ontrig | D19: このキャラが推理したとき、自分のデッキのカードを上から2枚見る。その中から特徴[探偵]のキャラを1枚まで公開して手札に加え、残りを好きな順番でデッキの下に移す。 | I19: →Ops | L19: ["reason"] | P19: self | AX19: 1
A20: id_0013 | B20: 1 | C20: flash | D20: 【ヒラメキ】(証拠からリムーブされるときに発動する)カードを1枚引く。 | I20: →Ops | AX20: 1
A21: id_0014 | B21: 0 | C21: onremoved | D21: 【相手ターン中】【現場リムーブ時】自分のデッキのカードを上からカード名[江戸川コナン]が出るまで1枚ずつ公開し、それを手札に加える。残りの公開したカードをデッキの下に移し、デッキをシャッフルする。 | F21: {"turn":"opp"} | I21: →Ops | AX21: 1
A22: id_0014 | B22: 1 | C22: flash | D22: 【ヒラメキ】(証拠からリムーブされるときに発動する)カードを1枚引く。 | I22: →Ops | AX22: 1
A23: id_0015 | B23: 0 | C23: cutin | D23: 【カットイン】AP+2000(コンタクト中に手札からリムーブして使う) | J23: 2000 | AX23: 0
A24: id_0016 | B24: 0 | C24: static | D24: このキャラがスリープ状態の場合、相手は自分の現場にいるレベル4以下のキャラを指定してアクションできない。 | F24: {"selfSt":"s"} | G24: {"sel":"allies","filter":{"lvMax":4}} | K24: noact | AX24: 0
A25: id_0016 | B25: 1 | C25: flash | D25: 【ヒラメキ】(証拠からリムーブされるときに発動する)キャラを1枚まで選び、スリープさせる。 | I25: →Ops | AX25: 1
A26: id_0017 | B26: 0 | C26: onplay | D26: 【登場時】レベル3以上のキャラの能力やレベル3以上のイベントの効果によって登場した場合、カードを1枚引く。 | F26: {"via":[{"type":"char","lvMin":3},{"type":"event","lvMin":3}]} | I26: →Ops | AX26: 1
A27: id_0018 | B27: 0 | C27: event | D27: 【パートナー】【青】手札を1枚リムーブする。自分のデッキのカードを上から6枚見る。その中からレベル4以下の特徴[少年探偵団]のキャラを2枚まで登場させ、残りをシャッフルしてデッキの下に移す。 | F27: {"pcolor":"blue"} | I27: →Ops | AX27: 5
A28: id_0019 | B28: 0 | C28: event | D28: 自分のデッキのカードを上から5枚見る。その中からカードを1枚まで手札に加え、残りを好きな順番でデッキの下に移す。このイベントを自分の現場にいるキャラ1枚にセットする。 | I28: →Ops | AX28: 2
A29: id_0019 | B29: 1 | C29: grant | D29: このイベントがセットされているキャラは「このキャラがコンタクトしたとき、そのコンタクト中、このキャラをAP+2000する。」を持つ。 | T29: {"ic":"oncontact","on":{"k":"atk"},"ops":[{"op":"self","do":"ap","v":"2000","until":"contact"}]} | AX29: 0
A30: id_0019 | B30: 2 | C30: flash | D30: 【ヒラメキ】(証拠からリムーブされるときに発動する) カードを1枚引く。 | I30: →Ops | AX30: 1
A31: id_0021 | B31: 0 | C31: static | D31: 【パートナー(緑)】LP+1 | F31: {"pcolor":"green"} | G31: {"sel":"self"} | X31: 1 | AX31: 0
A32: id_0021 | B32: 1 | C32: declare | D32: 【宣言】【スリープ】:カード名[服部平次]のキャラを1枚まで選び、ターン終了時まで突撃(登場したターンからすぐにアクションできる)を与える。 | H32: [{"c":"sleepSelf","n":1}] | I32: →Ops | AX32: 1
A33: id_0022 | B33: 0 | C33: static | D33: このキャラは相手の現場にいるアクティブ状態のキャラを指定してアクションできる。 | G33: {"sel":"self"} | K33: actactive | AX33: 0
A34: id_0022 | B34: 1 | C34: ontrig | D34: このキャラがコンタクトしたとき、そのコンタクト中、このキャラをAP+1000する。 | I34: →Ops | L34: ["contact"] | P34: self | AX34: 1
A35: id_0022 | B35: 2 | C35: ontrig | D35: 【パートナー(緑)】【自分ターン中】【ターン1】このキャラがコンタクトしたとき、このキャラをアクティブにする。 | E35: 1 | F35: {"pcolor":"green","turn":"self"} | I35: →Ops | L35: ["contact"] | P35: self | AX35: 1
A36: id_0023 | B36: 0 | C36: flash | D36: 【ヒラメキ】(証拠からリムーブされるときに発動する)カードを1枚引く。 | I36: →Ops | AX36: 1
A37: id_0024 | B37: 0 | C37: ontrig | D37: 【ターン1】相手の現場にいるキャラがコンタクトによってリムーブされたとき、自分のリムーブエリアにある【カットイン】を持つ【緑】のカードを1枚まで選び、手札に加える。 | E37: 1 | I37: →Ops | L37: ["removed"] | M37: opp | N37: {"type":"char","own":"opp"} | S37: contact | AX37: 1
A38: id_0025 | B38: 0 | C38: ontrig | D38: 相手の現場にいるキャラがコンタクトによってリムーブされたとき、ターン終了時までこのキャラは突撃(登場したターンからすぐにアクションできる)を持つ。 | I38: →Ops | L38: ["removed"] | M38: opp | N38: {"type":"char","own":"opp"} | S38: contact | AX38: 1
A39: id_0026 | B39: 0 | C39: ontrig | D39: 【ターン1】このキャラがアクション[キャラ]したとき、ターン終了時までこのキャラをAP+1000する。 | E39: 1 | I39: →Ops | L39: ["act"] | P39: self | V39: char | AX39: 1
A40: id_0027 | B40: 0 | C40: cutin | D40: 【カットイン】AP+2000(コンタクト中に手札からリムーブして使う) | J40: 2000 | AX40: 0
A41: id_0028 | B41: 0 | C41: onplay | D41: 【登場時】自分のデッキのカードを上から4枚見る。その中から【緑】のカードを1枚まで公開して手札に加え、残りを好きな順番でデッキの下に移す。カードを手札に加えた場合、手札を1枚リムーブする。 | I41: →Ops | AX41: 2
A42: id_0028 | B42: 1 | C42: flash | D42: 【ヒラメキ】(証拠からリムーブされるときに発動する)カードを1枚引く。 | I42: →Ops | AX42: 1
A43: id_0029 | B43: 0 | C43: onremoved | D43: 【現場リムーブ時】コンタクトによってリムーブされた場合、キャラを1枚まで選び、スリープさせる。 | F43: {"killed":true} | I43: →Ops | AX43: 1
A44: id_0029 | B44: 1 | C44: flash | D44: 【ヒラメキ】(証拠からリムーブされるときに発動する)カードを1枚引く。 | I44: →Ops | AX44: 1
A45: id_0030 | B45: 0 | C45: ontrig | D45: 【ターン1】自分の現場にいる【緑】のキャラがアクション[キャラ]したとき、キャラを1枚まで選び、スリープさせる。 | E45: 1 | I45: →Ops | L45: ["act"] | M45: self | N45: {"type":"char","color":"green","own":"self"} | V45: char | AX45: 1
A46: id_0031 | B46: 0 | C46: ontrig | D46: 【ターン1】自分の現場にいる【緑】のキャラがアクション[キャラ]したとき、カードを1枚引き、手札を1枚リムーブする。 | E46: 1 | I46: →Ops | L46: ["act"] | M46: self | N46: {"type":"char","color":"green","own":"self"} | V46: char | AX46: 2
A47: id_0031 | B47: 1 | C47: flash | D47: 【ヒラメキ】(証拠からリムーブされるときに発動する)カードを1枚引く。 | I47: →Ops | AX47: 1
A48: id_0032 | B48: 0 | C48: static | D48: 【自分ターン中】自分の現場にいるこのキャラ以外の【緑】のキャラをAP+1000する。 | F48: {"turn":"self"} | G48: {"sel":"allies","filter":{"color":"green"},"notSelf":true} | O48: 1000 | AX48: 0
A49: id_0032 | B49: 1 | C49: flash | D49: 【ヒラメキ】(証拠からリムーブされるときに発動する)カードを1枚引く。 | I49: →Ops | AX49: 1
A50: id_0033 | B50: 0 | C50: event | D50: このイベントを自分の現場にいる【緑】のキャラ1枚にセットする。 | I50: →Ops | AX50: 1
A51: id_0033 | B51: 1 | C51: grant | D51: このイベントがセットされているキャラが相手の能力や効果、コンタクトによって現場から離れるとき、このイベントをリムーブし、そのキャラは現場から離れる代わりに現場に残る。 | T51: {"ic":"replace","ef":{"self":true,"own":"self"},"forced":true,"rep":{"to":"stay","unsetSelf":true},"msg":"세트된 이벤트를 리무브하고 현장에 남습니다"} | AX51: 0
A52: id_0034 | B52: 0 | C52: event | D52: キャラを1枚まで選び、スリープさせる。カードを1枚引く。 | I52: →Ops | AX52: 2
A53: id_0034 | B53: 1 | C53: flash | D53: 【ヒラメキ】(証拠からリムーブされるときに発動する)キャラを1枚まで選び、スリープさせる。 | I53: →Ops | AX53: 1
A54: id_0036 | B54: 0 | C54: onplay | D54: 【パートナー(白)】【登場時】自分のデッキのカードを上から7枚リムーブしてもよい。そうした場合、キャラを1枚まで選び、デッキの下に移す。 | F54: {"pcolor":"white"} | I54: →Ops | AX54: 2
A55: id_0037 | B55: 0 | C55: static | D55: ミスリード1(相手の推理に対し、スリープさせることでLP-1する) | F55: {} | G55: {"sel":"self"} | K55: misread1 | AX55: 0
A56: id_0037 | B56: 1 | C56: ontrig | D56: 【ターン1】相手の現場にいるキャラが推理かアクションしたとき、自分のデッキのカードを上から5枚リムーブしてもよい。そうした場合、ターン終了時までそのキャラを元のLPを0にし、元のAPを0にする。 | E56: 1 | I56: →Ops | L56: ["reason","act"] | M56: opp | N56: {"type":"char","own":"opp"} | AX56: 2
A57: id_0038 | B57: 0 | C57: flash | D57: 【ヒラメキ】(証拠からリムーブされるときに発動する) カードを1枚引く。 | I57: →Ops | AX57: 1
A58: id_0039 | B58: 0 | C58: ontrig | D58: このキャラのアクション終了時、このキャラを現場からデッキの下に移してもよい。そうした場合、手札からレベル6以下の【白】のカード名[黒羽快斗]以外のキャラを1枚まで登場させる。ターン終了時までそのキャラに【突撃】(登場したターンからすぐにアクションできる)と「ターン終了時、このキャラを現場から手札に移す。」を与える。 | I58: →Ops | L58: ["actend"] | P58: self | AX58: 3
A59: id_0040 | B59: 0 | C59: declare | D59: 【宣言】【スリープ】:自分のデッキのカードを上から3枚見る。その中からカードを1枚手札に加え、残りを好きな順番でデッキの下に移す。 | H59: [{"c":"sleepSelf","n":1}] | I59: →Ops | AX59: 1
A60: id_0040 | B60: 1 | C60: flash | D60: 【ヒラメキ】(証拠からリムーブされるときに発動する)キャラを1枚まで選び、スリープさせる。 | I60: →Ops | AX60: 1
A61: id_0041 | B61: 0 | C61: static | D61: 【自分ターン中】相手の現場にキャラが3枚以上いる場合、このキャラをAP+2000する。 | F61: {"turn":"self","cnt":[{"src":"oppField","op":"ge","n":3}]} | G61: {"sel":"self"} | O61: 2000 | AX61: 0
A62: id_0042 | B62: 0 | C62: enter | D62: このキャラはスリープ状態で登場する。 | AE62: s | AX62: 0
A63: id_0042 | B63: 1 | C63: onplay | D63: 【登場時】自分のデッキのカードを上から1枚公開する。公開したカードが【白】のカードの場合、手札に加える。公開したカードがそれ以外の場合、デッキの下に移す。 | I63: →Ops | AX63: 1
A64: id_0042 | B64: 2 | C64: flash | D64: 【ヒラメキ】(証拠からリムーブされるときに発動する)カードを1枚引く。 | I64: →Ops | AX64: 1
A65: id_0043 | B65: 0 | C65: static | D65: 突撃[キャラ](登場したターンからすぐにキャラを指定してアクションできる) | F65: {} | G65: {"sel":"self"} | K65: assault-char | AX65: 0
A66: id_0043 | B66: 1 | C66: static | D66: このキャラは事件を指定してアクションできない。 | G66: {"sel":"self"} | K66: nocase | AX66: 0
A67: id_0043 | B67: 2 | C67: static | D67: 【自分ターン中】AP+1000 | F67: {"turn":"self"} | G67: {"sel":"self"} | O67: 1000 | AX67: 0
A68: id_0044 | B68: 0 | C68: enter | D68: このキャラはスリープ状態で登場する。 | AE68: s | AX68: 0
A69: id_0044 | B69: 1 | C69: onplay | D69: 【登場時】自分のデッキのカードを上から1枚公開する。公開したカードがレベル6以下のキャラの場合、登場させる。公開したカードがそれ以外の場合、手札に加える。 | I69: →Ops | AX69: 2
A70: id_0045 | B70: 0 | C70: onplay | D70: 【登場時】自分のデッキのカードを上から2枚見る。その中からLP2以上の【白】のキャラを1枚まで公開して手札に加え、残りを好きな順番でデッキの下に移す。 | I70: →Ops | AX70: 1
A71: id_0046 | B71: 0 | C71: onremoved | D71: 【相手ターン中】【現場リムーブ時】キャラを1枚まで選び、ターン終了時まで元のLPを0にする。 | F71: {"turn":"opp"} | I71: →Ops | AX71: 1
A72: id_0046 | B72: 1 | C72: flash | D72: 【ヒラメキ】(証拠からリムーブされるときに発動する)カードを1枚引く。 | I72: →Ops | AX72: 1
A73: id_0047 | B73: 0 | C73: onplay | D73: 【登場時】自分のデッキのカードを上から4枚見る。その中から【白】のカードを1枚まで公開して手札に加え、残りを好きな順番でデッキの下に移す。カードを手札に加えた場合、手札を1枚リムーブする。 | I73: →Ops | AX73: 2
A74: id_0047 | B74: 1 | C74: flash | D74: 【ヒラメキ】(証拠からリムーブされるときに発動する)カードを1枚引く。 | I74: →Ops | AX74: 1
A75: id_0048 | B75: 0 | C75: cutin | D75: 【カットイン】AP+2000(コンタクト中に手札からリムーブして使う) | J75: 2000 | AX75: 0
A76: id_0049 | B76: 0 | C76: event | D76: このイベントを自分の現場にいる【白】のキャラ1枚にセットする。 | I76: →Ops | AX76: 1
A77: id_0049 | B77: 1 | C77: grant | D77: このイベントがセットされているキャラは「【相手ターン中】【現場リムーブ時】手札からレベル7以下の【白】のキャラを1枚まで登場させる。」を持つ。 | T77: {"ic":"onremoved","cond":{"turn":"opp"},"ops":[{"op":"play","from":"hand","n":1,"filter":{"lvMax":7,"color":"white"}}],"txt":"【相手ターン中】【現場リムーブ時】手札からレベル7以下の【白】のキャラを1枚まで登場させる。。"} | AX77: 0
A78: id_0049 | B78: 2 | C78: flash | D78: 【ヒラメキ】(証拠からリムーブされるときに発動する)カードを1枚引く。 | I78: →Ops | AX78: 1
A79: id_0050 | B79: 0 | C79: event | D79: 【白】のキャラを1枚まで選び、ターン終了時まで【突撃[事件]】を与える。このターン中、次に相手の証拠がリムーブされたとき、スリープ状態のキャラを1枚まで選び、スタンさせる。(スタン状態のキャラをアクティブにする場合、代わりにスリープさせる) | I79: →Ops | AX79: 2
A80: id_0052 | B80: 0 | C80: ontrig | D80: 【パートナー】【赤】【ターン1】自分の現場にいるキャラがアクション[事件]したとき、レベル7以下のキャラを1枚まで選び、リムーブする。 | E80: 1 | F80: {"pcolor":"red"} | I80: →Ops | L80: ["act"] | M80: self | N80: {"type":"char","own":"self"} | V80: case | AX80: 1
A81: id_0052 | B81: 1 | C81: declare | D81: 【宣言】【ターン1】【赤】のキャラを1枚まで選び、ターン終了時までAP+1000する。 | E81: 1 | I81: →Ops | AX81: 1
A82: id_0053 | B82: 0 | C82: declare | D82: 【宣言】【スリープ】このキャラ以外のキャラを1枚スリープさせる:レベル7以下のキャラを1枚まで選び、リムーブする。 | H82: [{"c":"sleepSelf","n":1},{"c":"sleepAny","n":1,"filter":{"notSelf":true}}] | I82: →Ops | AX82: 1
A83: id_0054 | B83: 0 | C83: flash | D83: 【ヒラメキ】(証拠からリムーブされるときに発動する)カードを1枚引く。 | I83: →Ops | AX83: 1
A84: id_0055 | B84: 0 | C84: onremoved | D84: 【相手ターン中】【現場リムーブ時】相手に証拠を1つ与えてもよい。そうした場合、レベル5以下のキャラを1枚まで選び、リムーブする。 | F84: {"turn":"opp"} | I84: →Ops | AX84: 2
A85: id_0055 | B85: 1 | C85: flash | D85: 【ヒラメキ】(証拠からリムーブされるときに発動する)キャラを1枚まで選び、スリープさせる。 | I85: →Ops | AX85: 1
A86: id_0056 | B86: 0 | C86: ontrig | D86: 【ターン1】このキャラがアクション[事件]したとき、このキャラをアクティブにする。 | E86: 1 | I86: →Ops | L86: ["act"] | P86: self | V86: case | AX86: 1
A87: id_0057 | B87: 0 | C87: ontrig | D87: このキャラのアクション[事件]によって証拠を得たとき、相手の現場にいるレベル5以下のキャラを1枚まで選び、手札に移す。 | I87: →Ops | L87: ["evgain"] | P87: self | S87: action | V87: case | AX87: 1
A88: id_0058 | B88: 0 | C88: ontrig | D88: このキャラがアクション[事件]したとき、ターン終了時までこのキャラはバレット(このキャラのアクションはガードできない)を持つ。 | I88: →Ops | L88: ["act"] | P88: self | V88: case | AX88: 1
A89: id_0059 | B89: 0 | C89: onplay | D89: 【登場時】相手に証拠を1つ与えてもよい。そうした場合、カードを1枚引く。 | I89: →Ops | AX89: 2
A90: id_0060 | B90: 0 | C90: ontrig | D90: 相手の現場にいるキャラがこのキャラを指定してアクションしたとき、そのコンタクト中、このキャラをAP+1000する。 | I90: →Ops | L90: ["act"] | M90: opp | N90: {"type":"char","own":"opp"} | AC90: true | AX90: 1
A91: id_0060 | B91: 1 | C91: declare | D91: 【宣言】【スリープ】:キャラを1枚まで選び、ターン終了時までバレット(このキャラのアクションはガードできない)を与える。 | H91: [{"c":"sleepSelf","n":1}] | I91: →Ops | AX91: 1
A92: id_0060 | B92: 2 | C92: flash | D92: 【ヒラメキ】(証拠からリムーブされるときに発動する)カードを1枚引く。 | I92: →Ops | AX92: 1
A93: id_0061 | B93: 0 | C93: ontrig | D93: 【ターン1】自分の現場にいる特徴[FBI]のキャラがアクションしたとき、カードを1枚引く。 | E93: 1 | I93: →Ops | L93: ["act"] | M93: self | N93: {"type":"char","trait":"FBI","own":"self"} | AX93: 1
A94: id_0061 | B94: 1 | C94: ontrig | D94: 【ターン1】相手の現場にいるキャラが自分の現場にいる特徴[FBI]のキャラを指定してアクションしたとき、カードを1枚引く。 | E94: 1 | I94: →Ops | L94: ["act"] | M94: opp | N94: {"type":"char","own":"opp"} | AG94: {"type":"char","trait":"FBI","own":"self"} | AX94: 1
A95: id_0062 | B95: 0 | C95: onplay | D95: 【登場時】自分のデッキのカードを上から4枚見る。その中から【赤】のカードを1枚まで公開して手札に加え、残りを好きな順番でデッキの下に移す。カードを手札に加えた場合、手札を1枚リムーブする。 | I95: →Ops | AX95: 2
A96: id_0062 | B96: 1 | C96: flash | D96: 【ヒラメキ】(証拠からリムーブされるときに発動する)カードを1枚引く。 | I96: →Ops | AX96: 1
A97: id_0063 | B97: 0 | C97: cutin | D97: 【カットイン】AP+2000(コンタクト中に手札からリムーブして使う) | J97: 2000 | AX97: 0
A98: id_0064 | B98: 0 | C98: ontrig | D98: このキャラが推理したとき、相手は手札を公開する。(その後、元に戻す) | I98: →Ops | L98: ["reason"] | P98: self | AX98: 1
A99: id_0064 | B99: 1 | C99: flash | D99: 【ヒラメキ】(証拠からリムーブされるときに発動する) カードを1枚引く。 | I99: →Ops | AX99: 1
A100: id_0065 | B100: 0 | C100: ontrig | D100: 【相手ターン中】【ターン1】このキャラか自分の現場にいる【赤】のキャラがリムーブされたとき、カードを1枚引き、手札を1枚リムーブする。 | E100: 1 | F100: {"turn":"opp"} | I100: →Ops | L100: ["removed"] | N100: {"type":"char","color":"red","own":"self"} | P100: orSelf | AX100: 2
...

Sheet Ops
A1: card_id | B1: ab_index | C1: op_index | D1: op | E1: filter_own | F1: params
A2: id_0001 | B2: 0 | C2: 0 | D2: select | E2: any | F2: {"n":1,"do":"deckBottom","filter":{"type":"char","lvMax":"used"}}
A3: id_0002 | B3: 1 | C3: 0 | D3: play | F3: {"from":"hand","n":1,"filter":{"trait":"少年探偵団","lvMax":5}}
A4: id_0002 | B4: 1 | C4: 1 | D4: if | F4: {"c":"played","name":"江戸川コナン","ops":[{"op":"draw","n":1}]}
A5: id_0003 | B5: 0 | C5: 0 | D5: draw | F5: {"n":1}
A6: id_0003 | B6: 1 | C6: 0 | D6: self | F6: {"do":"ap","v":"1000"}
A7: id_0003 | B7: 1 | C7: 1 | D7: self | F7: {"do":"kw","v":"assault"}
A8: id_0004 | B8: 0 | C8: 0 | D8: draw | F8: {"n":1}
A9: id_0005 | B9: 1 | C9: 0 | D9: select | E9: any | F9: {"n":1,"filter":{"lpMax":0,"color":"blue"},"do":"active"}
A10: id_0006 | B10: 0 | C10: 0 | D10: discard | F10: {"n":1,"opt":true}
A11: id_0006 | B11: 0 | C11: 1 | D11: if | F11: {"c":"done","ops":[{"op":"gain","n":1}]}
A12: id_0007 | B12: 1 | C12: 0 | D12: draw | F12: {"n":1}
A13: id_0008 | B13: 0 | C13: 0 | D13: ent | F13: {"do":"active"}
A14: id_0008 | B14: 0 | C14: 1 | D14: ent | F14: {"do":"kw","v":"rapid"}
A15: id_0009 | B15: 0 | C15: 0 | D15: look | F15: {"n":2,"filter":{"type":"char","lpMax":0,"color":"blue"},"max":1,"then":"hand","rest":"bottom"}
A16: id_0010 | B16: 0 | C16: 0 | D16: select | E16: any | F16: {"n":1,"filter":{"lvMax":5},"do":"sleep"}
A17: id_0011 | B17: 0 | C17: 0 | D17: select | E17: any | F17: {"n":1,"filter":{},"do":"ap","v":"2000"}
A18: id_0012 | B18: 0 | C18: 0 | D18: look | F18: {"n":4,"filter":{"color":"blue"},"max":1,"then":"hand","rest":"bottom"}
A19: id_0012 | B19: 0 | C19: 1 | D19: if | F19: {"c":"done","ops":[{"op":"discard","n":1,"opt":false}]}
A20: id_0012 | B20: 1 | C20: 0 | D20: draw | F20: {"n":1}
A21: id_0013 | B21: 0 | C21: 0 | D21: look | F21: {"n":2,"filter":{"type":"char","trait":"探偵"},"max":1,"then":"hand","rest":"bottom"}
A22: id_0013 | B22: 1 | C22: 0 | D22: draw | F22: {"n":1}
A23: id_0014 | B23: 0 | C23: 0 | D23: reveal | F23: {"then":"hand","rest":"shuffleBottom","shuffle":true,"name":"江戸川コナン"}
A24: id_0014 | B24: 1 | C24: 0 | D24: draw | F24: {"n":1}
A25: id_0016 | B25: 1 | C25: 0 | D25: select | E25: any | F25: {"n":1,"filter":{},"do":"sleep"}
A26: id_0017 | B26: 0 | C26: 0 | D26: draw | F26: {"n":1}
A27: id_0018 | B27: 0 | C27: 0 | D27: discard | F27: {"n":1,"opt":false}
A28: id_0018 | B28: 0 | C28: 1 | D28: peek | F28: {"n":6,"reveal":false}
A29: id_0018 | B29: 0 | C29: 2 | D29: pick | F29: {"from":"seen","as":"chosen","reveal":false,"filter":{"type":"char","trait":"少年探偵団","lvMax":4},"n":2}
A30: id_0018 | B30: 0 | C30: 3 | D30: mv | F30: {"ref":"chosen","to":"field"}
A31: id_0018 | B31: 0 | C31: 4 | D31: mv | F31: {"ref":"rest","to":"deckBottom","order":"shuffle"}
A32: id_0019 | B32: 0 | C32: 0 | D32: look | F32: {"n":5,"filter":{},"max":1,"then":"hand","rest":"bottom"}
A33: id_0019 | B33: 0 | C33: 1 | D33: set
A34: id_0019 | B34: 2 | C34: 0 | D34: draw | F34: {"n":1}
A35: id_0021 | B35: 1 | C35: 0 | D35: select | E35: any | F35: {"n":1,"filter":{"name":"服部平次"},"do":"kw","v":"assault"}
A36: id_0022 | B36: 1 | C36: 0 | D36: self | F36: {"do":"ap","v":"1000","until":"contact"}
A37: id_0022 | B37: 2 | C37: 0 | D37: self | F37: {"do":"active"}
A38: id_0023 | B38: 0 | C38: 0 | D38: draw | F38: {"n":1}
A39: id_0024 | B39: 0 | C39: 0 | D39: fetch | F39: {"n":1,"from":"rem","filter":{"hasIc":"cutin","color":"green"}}
A40: id_0025 | B40: 0 | C40: 0 | D40: self | F40: {"do":"kw","v":"assault"}
A41: id_0026 | B41: 0 | C41: 0 | D41: self | F41: {"do":"ap","v":"1000"}
A42: id_0028 | B42: 0 | C42: 0 | D42: look | F42: {"n":4,"filter":{"color":"green"},"max":1,"then":"hand","rest":"bottom"}
A43: id_0028 | B43: 0 | C43: 1 | D43: if | F43: {"c":"done","ops":[{"op":"discard","n":1,"opt":false}]}
A44: id_0028 | B44: 1 | C44: 0 | D44: draw | F44: {"n":1}
A45: id_0029 | B45: 0 | C45: 0 | D45: select | E45: any | F45: {"n":1,"filter":{},"do":"sleep"}
A46: id_0029 | B46: 1 | C46: 0 | D46: draw | F46: {"n":1}
A47: id_0030 | B47: 0 | C47: 0 | D47: select | E47: any | F47: {"n":1,"filter":{},"do":"sleep"}
A48: id_0031 | B48: 0 | C48: 0 | D48: draw | F48: {"n":1}
A49: id_0031 | B49: 0 | C49: 1 | D49: discard | F49: {"n":1,"opt":false}
A50: id_0031 | B50: 1 | C50: 0 | D50: draw | F50: {"n":1}
A51: id_0032 | B51: 1 | C51: 0 | D51: draw | F51: {"n":1}
A52: id_0033 | B52: 0 | C52: 0 | D52: set | F52: {"filter":{"color":"green"}}
A53: id_0034 | B53: 0 | C53: 0 | D53: select | E53: any | F53: {"n":1,"filter":{},"do":"sleep"}
A54: id_0034 | B54: 0 | C54: 1 | D54: draw | F54: {"n":1}
A55: id_0034 | B55: 1 | C55: 0 | D55: select | E55: any | F55: {"n":1,"filter":{},"do":"sleep"}
A56: id_0036 | B56: 0 | C56: 0 | D56: deckrem | F56: {"n":7,"opt":true}
A57: id_0036 | B57: 0 | C57: 1 | D57: if | F57: {"c":"done","ops":[{"op":"select","n":1,"filter":{"own":"any"},"do":"deckBottom"}]}
A58: id_0037 | B58: 1 | C58: 0 | D58: deckrem | F58: {"n":5,"opt":true}
A59: id_0037 | B59: 1 | C59: 1 | D59: if | F59: {"c":"done","ops":[{"op":"ref","ref":"ent","acts":[{"do":"lpBase","v":"0"},{"do":"apBase","v":"0"}]}]}
A60: id_0038 | B60: 0 | C60: 0 | D60: draw | F60: {"n":1}
A61: id_0039 | B61: 0 | C61: 0 | D61: self | F61: {"do":"deckBottom","opt":true}
A62: id_0039 | B62: 0 | C62: 1 | D62: if | F62: {"c":"done","ops":[{"op":"play","from":"hand","n":1,"filter":{"nameNot":"黒羽快斗","lvMax":6,"color":"white"}}]}
A63: id_0039 | B63: 0 | C63: 2 | D63: ref | F63: {"ref":"played","acts":[{"do":"kw","v":"assault"},{"do":"gab","g":{"ic":"onend","ops":[{"op":"self","do":"hand"}],"txt":"自分のターン終了時、このキャラを現場から手札に移す。"}}]}
A64: id_0040 | B64: 0 | C64: 0 | D64: look | F64: {"n":3,"filter":{},"max":1,"then":"hand","rest":"bottom"}
A65: id_0040 | B65: 1 | C65: 0 | D65: select | E65: any | F65: {"n":1,"filter":{},"do":"sleep"}
A66: id_0042 | B66: 1 | C66: 0 | D66: revealTop | F66: {"n":1,"filter":{"color":"white"},"hit":"hand","miss":"bottom"}
A67: id_0042 | B67: 2 | C67: 0 | D67: draw | F67: {"n":1}
A68: id_0044 | B68: 1 | C68: 0 | D68: peek | F68: {"n":1,"reveal":true}
A69: id_0044 | B69: 1 | C69: 1 | D69: if | F69: {"c":"reg","ref":"revealed","all":true,"filters":[{"type":"char","lvMax":6}],"ops":[{"op":"mv","ref":"revealed","to":"field"}],"else":[{"op":"mv","ref":"revealed","to":"hand"}]}
A70: id_0045 | B70: 0 | C70: 0 | D70: look | F70: {"n":2,"filter":{"type":"char","lpMin":2,"color":"white"},"max":1,"then":"hand","rest":"bottom"}
A71: id_0046 | B71: 0 | C71: 0 | D71: select | E71: any | F71: {"n":1,"filter":{},"do":"lpBase","v":"0"}
A72: id_0046 | B72: 1 | C72: 0 | D72: draw | F72: {"n":1}
A73: id_0047 | B73: 0 | C73: 0 | D73: look | F73: {"n":4,"filter":{"color":"white"},"max":1,"then":"hand","rest":"bottom"}
A74: id_0047 | B74: 0 | C74: 1 | D74: if | F74: {"c":"done","ops":[{"op":"discard","n":1,"opt":false}]}
A75: id_0047 | B75: 1 | C75: 0 | D75: draw | F75: {"n":1}
A76: id_0049 | B76: 0 | C76: 0 | D76: set | F76: {"filter":{"color":"white"}}
A77: id_0049 | B77: 2 | C77: 0 | D77: draw | F77: {"n":1}
A78: id_0050 | B78: 0 | C78: 0 | D78: select | E78: any | F78: {"n":1,"filter":{"color":"white"},"do":"kw","v":"assault-case"}
A79: id_0050 | B79: 0 | C79: 1 | D79: delay | F79: {"evs":["evrem"],"who":"opp","ops":[{"op":"select","n":1,"filter":{"st":"s","own":"any"},"do":"stun"}]}
A80: id_0052 | B80: 0 | C80: 0 | D80: select | E80: any | F80: {"n":1,"filter":{"lvMax":7},"do":"remove"}
A81: id_0052 | B81: 1 | C81: 0 | D81: select | E81: any | F81: {"n":1,"filter":{"color":"red"},"do":"ap","v":"1000"}
A82: id_0053 | B82: 0 | C82: 0 | D82: select | E82: any | F82: {"n":1,"filter":{"lvMax":7},"do":"remove"}
A83: id_0054 | B83: 0 | C83: 0 | D83: draw | F83: {"n":1}
A84: id_0055 | B84: 0 | C84: 0 | D84: gain | F84: {"n":1,"who":"opp"}
A85: id_0055 | B85: 0 | C85: 1 | D85: if | F85: {"c":"done","ops":[{"op":"select","n":1,"do":"remove","filter":{"lvMax":5,"own":"any"}}]}
A86: id_0055 | B86: 1 | C86: 0 | D86: select | E86: any | F86: {"n":1,"filter":{},"do":"sleep"}
A87: id_0056 | B87: 0 | C87: 0 | D87: self | F87: {"do":"active"}
A88: id_0057 | B88: 0 | C88: 0 | D88: select | E88: opp | F88: {"n":1,"filter":{"lvMax":5},"do":"hand"}
A89: id_0058 | B89: 0 | C89: 0 | D89: self | F89: {"do":"kw","v":"bullet"}
A90: id_0059 | B90: 0 | C90: 0 | D90: gain | F90: {"n":1,"who":"opp","opt":true}
A91: id_0059 | B91: 0 | C91: 1 | D91: if | F91: {"c":"done","ops":[{"op":"draw","n":1}]}
A92: id_0060 | B92: 0 | C92: 0 | D92: self | F92: {"do":"ap","v":"1000","until":"contact"}
A93: id_0060 | B93: 1 | C93: 0 | D93: select | E93: any | F93: {"n":1,"filter":{},"do":"kw","v":"bullet"}
A94: id_0060 | B94: 2 | C94: 0 | D94: draw | F94: {"n":1}
A95: id_0061 | B95: 0 | C95: 0 | D95: draw | F95: {"n":1}
A96: id_0061 | B96: 1 | C96: 0 | D96: draw | F96: {"n":1}
A97: id_0062 | B97: 0 | C97: 0 | D97: look | F97: {"n":4,"filter":{"color":"red"},"max":1,"then":"hand","rest":"bottom"}
A98: id_0062 | B98: 0 | C98: 1 | D98: if | F98: {"c":"done","ops":[{"op":"discard","n":1,"opt":false}]}
A99: id_0062 | B99: 1 | C99: 0 | D99: draw | F99: {"n":1}
A100: id_0064 | B100: 0 | C100: 0 | D100: revealHand | F100: {"who":"opp"}
...

Sheet CardExtra
A1: card_id | B1: key | C1: value

Sheet Meta
A1: key | B1: value
A2: decks | B2: {}

Sheet Lists
A1: type | B1: color | C1: ic | D1: op | E1: own | F1: ※ 현재 cards.json 에 실제 존재하는 값입니다 (참고/드롭다운용).
A2: case | B2: black | C2: cutin | D2: blankAb | E2: self
A3: char | B3: blue | C3: deckfree | D3: blockActGain | E3: opp
A4: event | B4: blue/black | C4: declare | D4: bottomSame | E4: any
A5: partner | B5: blue/green | C5: disguise | D5: charToEvid
B6: blue/white | C6: enter | D6: choose
B7: blue/yellow | C7: event | D7: chooseMulti
B8: green | C8: flash | D8: contact
B9: green/blue | C9: grant | D9: deckRemSome
B10: green/white | C10: hand | D10: deckSink
B11: green/yellow | C11: ignorecolor | D11: deckToFile
B12: purple | C12: mr | D12: deckrem
B13: red | C13: onact | D13: delay
B14: red/black | C14: onally | D14: discard
B15: red/blue | C15: onallycontact | D15: draw
B16: red/blue/green/yellow | C16: onallykill | D16: ent
B17: red/blue/green/yellow/white/black | C17: onallyremoved | D17: entDo
... B23: yellow/black | C23: onkill | D23: flashFlipped
C24: onmain | D24: flashPickOne
C25: onplay | D25: flip
C26: onreason | D26: flipAllEvid
C27: onremleave | D27: flipDown
C28: onremoved | D28: flipEvid
C29: onsolve | D29: flipTopEvid
C30: ontrig | D30: gain
C31: replace | D31: handTo
C32: static | D32: hayIgn
C33: usecond | D33: if
C34: winalt | D34: ifCost
D35: ifLeft
D36: ifSelf
D37: ifUse
D38: ifc
D39: invest2
D40: investigate
D41: look
D42: loseEvid
D43: lvBudgetRm
D44: moveSet
D45: moveUnder
D46: mv
... D103: winGame
